Workbook
Name dwsrf_funding_tracker_all_projects: dwsrf_tracker!$A$1:$R$14802

Sheet metadata
A1: Tab | B1: Description | C1: Source | D1: URL | E1: Notes
A2: tot_allotment | B2: Allotment summary | C2: Katy compiled
A3: overtime | B3: Data of # proj and amount overtime | C3: CRS | D3: https://www.congress.gov/crs-product/R48066
A4: CW_23_cap | B4: Allotment for 23 | C4: EPA | D4: https://www.epa.gov/system/files/documents/2023-03/fy2023-cwsrf-base-allotment.pdf
A5: DW_23_cap | B5: Allotment for 23 | C5: EPA | D5: https://www.epa.gov/system/files/documents/2023-04/Final_FY23%20DWSRF%20Allotment%20Memo%20and%20Attachments_April%202023.pdf
A6: cds_23 | B6: Earmarks | C6: Congress | D6: https://www.appropriations.senate.gov/imo/media/doc/INTERIOR_DISCL_20221218.pdf | E6: Katy digitized
A7: CW_24_cap | B7: Allotment for 24 | C7: EPA | D7: https://www.epa.gov/system/files/documents/2024-04/fy24-joint-srf-allotments-memorandum-attachments.pdf
A8: DW_24_cap | B8: Allotment for 24 | C8: EPA | D8: https://www.epa.gov/system/files/documents/2024-04/fy24-joint-srf-allotments-memorandum-attachments.pdf
A9: cds_24 | B9: Earmarks | C9: Congress | E9: EPIC digitized | F9: https://docs.google.com/spreadsheets/d/1GMUcOXnIPlLiP-Oh_cEPAnCZPpCLsGI-/edit?gid=1942082838#gid=1942082838
A10: dwsrf_tracker | B10: All tracker data | C10: IUPs/PPLs from EPIC

Sheet tot_allotment
B1: FY21 | C1: FY22 | D1: FY23 | E1: FY24 | F1: FY25
B2: CW | C2: CW | D2: CW | E2: CW | F2: CW
A3: Funds Available to States | D3: 757737000 | E3: 824644000
A4: Tribal Set-Aside | D4: 15515000 | E4: 16880000
A5: Clean Watersheds Needs Survery | D5: 1500000 | E5: 1500000
A6: National American Iron & Steel Administrative Set-Aside | D6: 1000358 | E6: 1000733
A7: CDS | D7: 863108642 | E7: 787652267
A8: CDS Administration | E8: 7184000
A9: Total Appropriation | D9: 1638861000 | E9: 1638861000
A10: Base - set asides: | D10: =D9-SUM(D4:D6) -> 1620845642 | E10: =E9-SUM(E4:E6) -> 1619480267
B12: DW | C12: DW | D12: DW | E12: DW | F12: DW
A13: Funds Available to States | D13: 493785000 | E13: 466058000
A14: Tribal Set-Aside | D14: 10332000 | E14: 9767000
A15: Monitoring for Unregulated Contaminants | D15: 12000000 | E15: 12000000
A16: National American Iron & Steel Administrative Set-Aside | D16: 728101 | E16: 500095
A17: CDS | D17: 609255899 | E17: 631659905
A18: CDS Administration | E18: 6116000
A19: Total Appropriation | D19: 1126101000 | E19: 1126101000
A20: Base - set asides: | D20: =D19-SUM(D14:D16) -> 1103040899 | E20: =E19-SUM(E14:E16) -> 1103833905

Sheet overtime
A1: Fiscal Year | B1: # of Projects | C1: Total Earmarked Funds for Project Grants | D1: Available for CWSRF Capitalization Grants | E1: Available for DWSRF Capitalization Grants
A2: 1989 | B2: 4 | C2: 68 | D2: 941 | E2: —
A3: 1990 | B3: 4 | C3: 53 | D3: 967 | E3: —
A4: 1991 | B4: 2 | C4: 36 | D4: 2048 | E4: —
A5: 1992 | B5: 8 | C5: 435 | D5: 1949 | E5: —
A6: 1993 | B6: 13 | C6: 556 | D6: 1928 | E6: —
A7: 1994 | B7: 9 | C7: 558 | D7: 1218 | E7: —
A8: 1995 | B8: 46 | C8: 834 | D8: 1235 | E8: —
A9: 1996 | B9: 20 | C9: 307 | D9: 2074 | E9: —
A10: 1997 | B10: 21 | C10: 301 | D10: 625 | E10: 1275
A11: 1998 | B11: 42 | C11: 393 | D11: 1350 | E11: 725
A12: 1999 | B12: 82 | C12: 402 | D12: 1350 | E12: 775
A13: 2000 | B13: 143 | C13: 395 | D13: 1345 | E13: 820
A14: 2001 | B14: 244 | C14: 466 | D14: 1350 | E14: 825
A15: 2002 | B15: 339 | C15: 459 | D15: 1350 | E15: 850
A16: 2003 | B16: 491 | C16: 413 | D16: 1341 | E16: 845
A17: 2004 | B17: 520 | C17: 425 | D17: 1342 | E17: 845
A18: 2005 | B18: 669 | C18: 402 | D18: 1091 | E18: 843
A19: 2006 | B19: 259 | C19: 289 | D19: 887 | E19: 838
A20: 2007 | B20: 2 | C20: 84 | D20: 1084 | E20: 838
A21: 2008 | B21: 282 | C21: 177 | D21: 689 | E21: 829
... A34: 2021 | B34: 0 | C34: 0 | D34: 1639 | E34: 1126
A35: 2022 | B35: 485 | C35: 841 | D35: 3195 | E35: $6,430‬
A36: 2023 | B36: 715 | C36: 1472 | D36: $3,200‬ | E36: 6519
A37: 2024 | B37: 1035 | C37: 1458
A38: 2025 | B38: 0

Sheet CW_23_cap
A1: state | B1: allotment | C1: pct
A2: Alabama | B2: 8473000 | C2: =B2/tot_allotment!$D$3 -> 0.01118198
A3: Alaska | B3: 4535000 | C3: =B3/tot_allotment!$D$3 -> 0.0059849262
A4: Arizona | B4: 5118000 | C4: =B4/tot_allotment!$D$3 -> 0.0067543224
A5: Arkansas | B5: 4957000 | C5: =B5/tot_allotment!$D$3 -> 0.0065418476
A6: California | B6: 54191000 | C6: =B6/tot_allotment!$D$3 -> 0.071516898
A7: Colorado | B7: 6061000 | C7: =B7/tot_allotment!$D$3 -> 0.0079988175
A8: Connecticut | B8: 9282000 | C8: =B8/tot_allotment!$D$3 -> 0.012249633
A9: Delaware | B9: 3720000 | C9: =B9/tot_allotment!$D$3 -> 0.0049093551
A10: Florida | B10: 25576000 | C10: =B10/tot_allotment!$D$3 -> 0.033753136
A11: Georgia | B11: 12811000 | C11: =B11/tot_allotment!$D$3 -> 0.016906922
A12: Hawaii | B12: 5868000 | C12: =B12/tot_allotment!$D$3 -> 0.0077441117
A13: Idaho | B13: 3720000 | C13: =B13/tot_allotment!$D$3 -> 0.0049093551
... A52: Wyoming | B52: 3720000 | C52: =B52/tot_allotment!$D$3 -> 0.0049093551

Sheet DW_23_cap
A1: state | B1: allotment | C1: pct
A2: Alabama | B2: 8719000 | C2: 0.0177
A3: Alaska | B3: 4938000 | C3: 0.01
A4: Arizona | B4: 8638000 | C4: 0.0175
A5: Arkansas | B5: 5912000 | C5: 0.012
A6: California | B6: 53272000 | C6: 0.1079
A7: Colorado | B7: 8650000 | C7: 0.0175
A8: Connecticut | B8: 4938000 | C8: 0.01
A9: Delaware | B9: 4938000 | C9: 0.01
A10: Florida | B10: 17820000 | C10: 0.0361
A11: Georgia | B11: 13389000 | C11: 0.0271
A12: Hawaii | B12: 4938000 | C12: 0.01
A13: Idaho | B13: 4938000 | C13: 0.01
... A52: Wyoming | B52: 4938000 | C52: 0.01

Sheet cds_23
A1: Agency | B1: Account | C1: State | D1: Project | E1: Amount | F1: House_Requestor | G1: Senate_Requestor | H1: Origination
A2: Environmental Protection Agency | B2: STAG— Drinking Water State Revolving Fund | C2: AK | D2: City of Whittier for Well Field Upgrades | E2: 1230000 | G2: Murkowski | H2: S
A3: Environmental Protection Agency | B3: STAG— Drinking Water State Revolving Fund | C3: AK | D3: Chickaloon Village Traditional Council for Community Well in Chickaloon | E3: 250000 | G3: Murkowski | H3: S
A4: Environmental Protection Agency | B4: STAG— Drinking Water State Revolving Fund | C4: AK | D4: City and Borough of Yakutat for Waterline Extension Project | E4: 5082000 | G4: Murkowski | H4: S
A5: Environmental Protection Agency | B5: STAG— Drinking Water State Revolving Fund | C5: AK | D5: City of Nome for Potable Water Distribution and Wastewater Collection Systems | E5: 1600000 | G5: Murkowski | H5: S
A6: Environmental Protection Agency | B6: STAG— Drinking Water State Revolving Fund | C6: AL | D6: Town of Garden City Water System Im- provements | E6: 520000 | F6: Aderholt | H6: H
A7: Environmental Protection Agency | B7: STAG— Drinking Water State Revolving Fund | C7: AL | D7: Mobile County Water, Sewer, and Fire Pro- tection Authority Water Well Project | E7: 1280000 | F7: Carl | H7: H
A8: Environmental Protection Agency | B8: STAG— Drinking Water State Revolving Fund | C8: AR | D8: Fulton Waterworks for City of Fulton Water System Delivery | E8: 3050000 | G8: Boozman | H8: S
A9: Environmental Protection Agency | B9: STAG— Drinking Water State Revolving Fund | C9: AR | D9: Central Arkansas Water for West Pulaski County Water Delivery | E9: 12000000 | G9: Boozman | H9: S
A10: Environmental Protection Agency | B10: STAG— Drinking Water State Revolving Fund | C10: AZ | D10: Bullhead City for New Drinking Water Well Construction Project | E10: 2000000 | G10: Kelly | H10: S
A11: Environmental Protection Agency | B11: STAG— Drinking Water State Revolving Fund | C11: AZ | D11: Town of Carefree for Silver Saddle Pres- sure Zone Waterline Improvement Project | E11: 800000 | G11: Kelly | H11: S
A12: Environmental Protection Agency | B12: STAG— Drinking Water State Revolving Fund | C12: AZ | D12: City of Page for Water Treatment Plant Ex- pansion Project | E12: 456000 | G12: Kelly | H12: S
A13: Environmental Protection Agency | B13: STAG— Drinking Water State Revolving Fund | C13: AZ | D13: City of Douglas for a Supervisory Control and Data Acquisition System | E13: 833285 | F13: Kirkpatrick | G13: Sinema | H13: H
A14: Environmental Protection Agency | B14: STAG— Drinking Water State Revolving Fund | C14: AZ | D14: Town of Kearny for a Water Infrastructure Project | E14: 3000000 | F14: O’Halleran | H14: H
A15: Environmental Protection Agency | B15: STAG— Drinking Water State Revolving Fund | C15: AZ | D15: Hopi Tribe for a Water Infrastructure Im- provement Project | E15: 1500000 | F15: O’Halleran | G15: Kelly, Sinema | H15: H
A16: Environmental Protection Agency | B16: STAG— Drinking Water State Revolving Fund | C16: AZ | D16: Maricopa-Stanfield Irrigation and Drainage District for the Santa Rosa Canal Project | E16: 2846076 | F16: O’Halleran | G16: Kelly, Sinema | H16: H/S
A17: Environmental Protection Agency | B17: STAG— Drinking Water State Revolving Fund | C17: AZ | D17: City of Page for New Intake Pipes from Lake Powell | E17: 3432000 | F17: O’Halleran | G17: Sinema | H17: H/S
A18: Environmental Protection Agency | B18: STAG— Drinking Water State Revolving Fund | C18: CA | D18: East Palo Alto for East Palo Alto Water In- frastructure Improvements | E18: 800000 | G18: Feinstein | H18: S
A19: Environmental Protection Agency | B19: STAG— Drinking Water State Revolving Fund | C19: CA | D19: County of Tulare for Drinking Water Kiosks | E19: 200000 | G19: Feinstein, Padilla | H19: S
A20: Environmental Protection Agency | B20: STAG— Drinking Water State Revolving Fund | C20: CA | D20: Woodville Public Utility District for Wood- ville PUD Well No. 4 Replacement | E20: 1150000 | G20: Feinstein, Padilla | H20: S
A21: Environmental Protection Agency | B21: STAG— Drinking Water State Revolving Fund | C21: CA | D21: City of Modesto for Grayson Well and Tank Replacement | E21: 1750000 | G21: Feinstein, Padilla | H21: S
A22: Environmental Protection Agency | B22: STAG— Drinking Water State Revolving Fund | C22: CA | D22: Allensworth Community Services District for Allensworth Well Solar Array | E22: 150000 | G22: Feinstein, Padilla | H22: S
A23: Environmental Protection Agency | B23: STAG— Drinking Water State Revolving Fund | C23: CA | D23: City of Tulare for Water Delivery System | E23: 500000 | G23: Feinstein, Padilla | H23: S
A24: Environmental Protection Agency | B24: STAG— Drinking Water State Revolving Fund | C24: CA | D24: City of Dinuba for Well 21 Construction | E24: 1500000 | G24: Padilla | H24: S
A25: Environmental Protection Agency | B25: STAG— Drinking Water State Revolving Fund | C25: CA | D25: Carmichael Water District for Aquifer Stor- age and Recharge Well #2 | E25: 2500000 | F25: Bera | H25: H
A26: Environmental Protection Agency | B26: STAG— Drinking Water State Revolving Fund | C26: CA | D26: Citrus Heights Water District for the High- land Avenue Well Project | E26: 1500000 | F26: Bera | H26: H
A27: Environmental Protection Agency | B27: STAG— Drinking Water State Revolving Fund | C27: CA | D27: Sacramento County for a Regional Con- junctive Use Project | E27: 2800000 | F27: Bera | G27: Padilla | H27: H
A28: Environmental Protection Agency | B28: STAG— Drinking Water State Revolving Fund | C28: CA | D28: City of Oxnard for a Water Pipeline Re- placement | E28: 2846400 | F28: Brownley | G28: Feinstein, Padilla | H28: H
A29: Environmental Protection Agency | B29: STAG— Drinking Water State Revolving Fund | C29: CA | D29: Cachuma Operation and Maintenance Board for the Lake Cachuma Pumping Facility Project | E29: 500000 | F29: Carbajal | G29: Feinstein | H29: H
A30: Environmental Protection Agency | B30: STAG— Drinking Water State Revolving Fund | C30: CA | D30: City of Atwater for the Buhach Road and Gurr Road Utility Extension | E30: 3000000 | F30: Costa | H30: H
A31: Environmental Protection Agency | B31: STAG— Drinking Water State Revolving Fund | C31: CA | D31: Solano Irrigation District for Quail Creek Well Relocation and Associated Convey- ance Facilities | E31: 2824000 | F31: Garamendi | G31: Padilla | H31: H
A32: Environmental Protection Agency | B32: STAG— Drinking Water State Revolving Fund | C32: CA | D32: City of Ripon for the SSJID Surface Water Connection Project | E32: 3452972 | F32: Harder (CA) | H32: H
A33: Environmental Protection Agency | B33: STAG— Drinking Water State Revolving Fund | C33: CA | D33: Stanislaus County for a Crows Landing Water Wells Project | E33: 3452972 | F33: Harder (CA) | G33: Padilla | H33: H
A34: Environmental Protection Agency | B34: STAG— Drinking Water State Revolving Fund | C34: CA | D34: Valley Center Municipal Water District Lilac Road Pipeline Replacement Project | E34: 3060000 | F34: Issa | G34: Feinstein, Padilla | H34: H
A35: Environmental Protection Agency | B35: STAG— Drinking Water State Revolving Fund | C35: CA | D35: Borrego Water District—Borrego Spring Road Transmission Main and Sun Gold Pipeline Replacement Projects | E35: 3392667 | F35: Issa | G35: Padilla | H35: H
A36: Environmental Protection Agency | B36: STAG— Drinking Water State Revolving Fund | C36: CA | D36: Orange County Water District PFAS Groundwater Treatment Project | E36: 5000000 | F36: Kim (CA) | G36: Padilla | H36: H
A37: Environmental Protection Agency | B37: STAG— Drinking Water State Revolving Fund | C37: CA | D37: Placer County Water Agency Alta Loop Pipeline Project | E37: 1000000 | F37: LaMalfa | H37: H
A38: Environmental Protection Agency | B38: STAG— Drinking Water State Revolving Fund | C38: CA | D38: City of Sacramento for the Shasta Ground- water Well Project | E38: 3452972 | F38: Matsui | H38: H
A39: Environmental Protection Agency | B39: STAG— Drinking Water State Revolving Fund | C39: CA | D39: City of Azusa for Aspan Well Treatment and Rehabilitation | E39: 2500000 | F39: Napolitano | H39: H
A40: Environmental Protection Agency | B40: STAG— Drinking Water State Revolving Fund | C40: CA | D40: City of Salinas for the Castroville Seawater Intrusion Project | E40: 900000 | F40: Panetta | G40: Feinstein, Padilla | H40: H
A41: Environmental Protection Agency | B41: STAG— Drinking Water State Revolving Fund | C41: CA | D41: Soquel Creek Water District for a Water Reliability Improvement Project | E41: 1416000 | F41: Panetta | G41: Padilla | H41: H
A42: Environmental Protection Agency | B42: STAG— Drinking Water State Revolving Fund | C42: CA | D42: City of Hemet for the Oakland and Santa Fe Water Main Replacement Project | E42: 1200000 | F42: Ruiz | H42: H
A43: Environmental Protection Agency | B43: STAG— Drinking Water State Revolving Fund | C43: CA | D43: Coachella Valley Water District for a Water Consolidation Project | E43: 3452972 | F43: Ruiz | G43: Feinstein, Padilla | H43: H
A44: Environmental Protection Agency | B44: STAG— Drinking Water State Revolving Fund | C44: CA | D44: City of Santa Fe Springs for Water Well No. 12 Assessment and Treatment | E44: 2200000 | F44: Sanchez | H44: H
A45: Environmental Protection Agency | B45: STAG— Drinking Water State Revolving Fund | C45: CA | D45: Water Replenishment District of Southern California for Five Groundwater Well Projects | E45: 2500000 | F45: Sanchez | G45: Padilla | H45: H
A46: Environmental Protection Agency | B46: STAG— Drinking Water State Revolving Fund | C46: CA | D46: City of Pleasanton for a PFAS Treatment and Well Rehabilitation Project | E46: 2000000 | F46: Swalwell | G46: Feinstein, Padilla | H46: H
A47: Environmental Protection Agency | B47: STAG— Drinking Water State Revolving Fund | C47: CA | D47: Eastern Municipal Water District for the Well 56 & 57 PFAS Removal Project | E47: 3452972 | F47: Takano | G47: Feinstein, Padilla | H47: H
A48: Environmental Protection Agency | B48: STAG— Drinking Water State Revolving Fund | C48: CA | D48: City of Pomona for Groundwater Treatment R34 | E48: 1600000 | F48: Torres (CA) | H48: H
A49: Environmental Protection Agency | B49: STAG— Drinking Water State Revolving Fund | C49: CA | D49: City of Chino for a Treatment Plant Groundwater Wells 4 & 6 Project | E49: 2000000 | F49: Torres (CA) | H49: H
A50: Environmental Protection Agency | B50: STAG— Drinking Water State Revolving Fund | C50: CA | D50: City of Fowler New Well and System Inter- connection for Drought Resiliency Project | E50: 3005200 | F50: Valadao | H50: H
A51: Environmental Protection Agency | B51: STAG— Drinking Water State Revolving Fund | C51: CA | D51: City of Inglewood for a Water Main Re- placement Project | E51: 3452972 | F51: Waters | H51: H
A52: Environmental Protection Agency | B52: STAG— Drinking Water State Revolving Fund | C52: CO | D52: Beulah Water Works District for Raw Water Storage | E52: 380000 | G52: Bennet, Hickenlooper | H52: S
A53: Environmental Protection Agency | B53: STAG— Drinking Water State Revolving Fund | C53: CO | D53: Town of Naturita for Wastewater Treatment Plant Lagoon Upgrade and Collection System | E53: 1250000 | G53: Bennet, Hickenlooper | H53: S
A54: Environmental Protection Agency | B54: STAG— Drinking Water State Revolving Fund | C54: CO | D54: City of Delta for North Delta Water Line Replacement | E54: 380000 | G54: Bennet, Hickenlooper | H54: S
A55: Environmental Protection Agency | B55: STAG— Drinking Water State Revolving Fund | C55: CO | D55: City of Trinidad for a Drinking Water Infra- structure Project | E55: 1149000 | G55: Hickenlooper | H55: S
A56: Environmental Protection Agency | B56: STAG— Drinking Water State Revolving Fund | C56: CO | D56: Town of Cheraw for a Regional Consolida- tion Project | E56: 1625000 | G56: Hickenlooper | H56: S
A57: Environmental Protection Agency | B57: STAG— Drinking Water State Revolving Fund | C57: CO | D57: Town of Superior for Granular Activated Carbon System at Water Treatment Plant | E57: 1280000 | G57: Hickenlooper | H57: S
A58: Environmental Protection Agency | B58: STAG— Drinking Water State Revolving Fund | C58: CO | D58: City of Aurora for a Waterline Replacement Program | E58: 2800000 | F58: Crow | G58: Bennet, Hickenlooper | H58: H
A59: Environmental Protection Agency | B59: STAG— Drinking Water State Revolving Fund | C59: CO | D59: Town of Minturn for a Water Treatment Plant | E59: 2000000 | F59: Neguse | G59: Bennet | H59: H
A60: Environmental Protection Agency | B60: STAG— Drinking Water State Revolving Fund | C60: CO | D60: City of Northglenn for Water Treatment Plant Improvements | E60: 2329600 | F60: Perlmutter | G60: Hickenlooper | H60: H
A61: Environmental Protection Agency | B61: STAG— Drinking Water State Revolving Fund | C61: CT | D61: School Hill Water Association for Clean Water for the School Hill Association | E61: 1200000 | G61: Blumenthal, Murphy | H61: S
A62: Environmental Protection Agency | B62: STAG— Drinking Water State Revolving Fund | C62: CT | D62: The South Central Regional Water Authority for Lake Gaillard Water Treatment Plant HVAC and Electrical Improvements | E62: 2647000 | G62: Blumenthal, Murphy | H62: S
A63: Environmental Protection Agency | B63: STAG— Drinking Water State Revolving Fund | C63: CT | D63: The South Central Regional Water Authority for Seymour Well Treatment Facility Generator Replacement | E63: 716000 | G63: Blumenthal, Murphy | H63: S
A64: Environmental Protection Agency | B64: STAG— Drinking Water State Revolving Fund | C64: CT | D64: The Metropolitan District Commission for Northeast Transmission Water Main | E64: 2500000 | G64: Blumenthal, Murphy | H64: S
A65: Environmental Protection Agency | B65: STAG— Drinking Water State Revolving Fund | C65: CT | D65: Norwich Public Utilities for Poquetanuck Cove Crossing Water Interconnect | E65: 800000 | G65: Blumenthal, Murphy | H65: S
A66: Environmental Protection Agency | B66: STAG— Drinking Water State Revolving Fund | C66: DE | D66: City of Dover for Water Main Extension and New Well | E66: 1800000 | G66: Carper, Coons | H66: S
A67: Environmental Protection Agency | B67: STAG— Drinking Water State Revolving Fund | C67: FL | D67: City of Fort Myers Water Treatment Expan- sion Plan | E67: 2500000 | F67: Donalds | H67: H
A68: Environmental Protection Agency | B68: STAG— Drinking Water State Revolving Fund | C68: FL | D68: Town of Lantana for a Water Main Repair Project | E68: 1200000 | F68: Frankel, Lois | H68: H
A69: Environmental Protection Agency | B69: STAG— Drinking Water State Revolving Fund | C69: FL | D69: Village of Pinecrest Waterline Lateral Con- nection Project | E69: 640000 | F69: Salazar | H69: H
A70: Environmental Protection Agency | B70: STAG— Drinking Water State Revolving Fund | C70: FL | D70: DeSoto County for the Restoration of Shoreline Off the Peace River in DeSoto County | E70: 2500000 | F70: Steube | H70: H
A71: Environmental Protection Agency | B71: STAG— Drinking Water State Revolving Fund | C71: FL | D71: Lee County for the North Lee County Wellfield Expansion Project | E71: 2400000 | F71: Steube | H71: H
A72: Environmental Protection Agency | B72: STAG— Drinking Water State Revolving Fund | C72: FL | D72: City of Hollywood for Membrane Softening Drinking Water Upgrades | E72: 3452972 | F72: Wasserman Schultz | H72: H
A73: Environmental Protection Agency | B73: STAG— Drinking Water State Revolving Fund | C73: GA | D73: City of Byron for Walker Road Drinking Water Improvement | E73: 651000 | G73: Ossoff | H73: S
A74: Environmental Protection Agency | B74: STAG— Drinking Water State Revolving Fund | C74: GA | D74: Augusta-Richmond County for Water Line Evaluation | E74: 1000000 | G74: Warnock | H74: S
A75: Environmental Protection Agency | B75: STAG— Drinking Water State Revolving Fund | C75: GA | D75: City of Keysville for Water Supply and Water Source Lines | E75: 197000 | G75: Warnock | H75: S
A76: Environmental Protection Agency | B76: STAG— Drinking Water State Revolving Fund | C76: GA | D76: Gwinnett County for Replacement and Up- grade of Aged Water Distribution Mains | E76: 2988000 | F76: Bourdeaux | H76: H
A77: Environmental Protection Agency | B77: STAG— Drinking Water State Revolving Fund | C77: GA | D77: City of East Point for a Water Main Up- grade Project | E77: 1600000 | F77: Williams (GA) | G77: Warnock | H77: H
A78: Environmental Protection Agency | B78: STAG— Drinking Water State Revolving Fund | C78: HI | D78: County of Hawai’i for North Kona Deep Well | E78: 2080000 | G78: Hirono, Schatz | H78: S
A79: Environmental Protection Agency | B79: STAG— Drinking Water State Revolving Fund | C79: HI | D79: County of Hawai’i for Large Water Meter Replacement | E79: 80000 | G79: Hirono, Schatz | H79: S
A80: Environmental Protection Agency | B80: STAG— Drinking Water State Revolving Fund | C80: IL | D80: City of Chicago for Daycare Lead Service Line Replacement | E80: 1000000 | G80: Duckworth | H80: S
A81: Environmental Protection Agency | B81: STAG— Drinking Water State Revolving Fund | C81: IL | D81: City of Edwardsville for Cass Avenue Water Main Replacement | E81: 500000 | G81: Durbin | H81: S
A82: Environmental Protection Agency | B82: STAG— Drinking Water State Revolving Fund | C82: IL | D82: Village of Ivesdale for Water Main Im- provements | E82: 250000 | G82: Durbin | H82: S
A83: Environmental Protection Agency | B83: STAG— Drinking Water State Revolving Fund | C83: IL | D83: Villages of Bedford Park & Lemont for Water Connection Project | E83: 500000 | G83: Durbin | H83: S
A84: Environmental Protection Agency | B84: STAG— Drinking Water State Revolving Fund | C84: IL | D84: City of Centralia for Water Line Replace- ment | E84: 500000 | G84: Durbin | H84: S
A85: Environmental Protection Agency | B85: STAG— Drinking Water State Revolving Fund | C85: IL | D85: City of Quincy for Lead Service Line Re- placement | E85: 400000 | G85: Durbin | H85: S
A86: Environmental Protection Agency | B86: STAG— Drinking Water State Revolving Fund | C86: IL | D86: DuPage County for York Township Drinking Water Project | E86: 300000 | G86: Durbin | H86: S
A87: Environmental Protection Agency | B87: STAG— Drinking Water State Revolving Fund | C87: IL | D87: City of Waukegan for Lead Service Line Replacement | E87: 500000 | G87: Durbin | H87: S
A88: Environmental Protection Agency | B88: STAG— Drinking Water State Revolving Fund | C88: IL | D88: City of Lewistown for a Municipal Water Supply Project | E88: 600000 | F88: Bustos | H88: H
A89: Environmental Protection Agency | B89: STAG— Drinking Water State Revolving Fund | C89: IL | D89: City of Litchfield Drinking Water Distribu- tion System Improvements Phase I & II | E89: 2284429 | F89: Davis, Rodney | H89: H
A90: Environmental Protection Agency | B90: STAG— Drinking Water State Revolving Fund | C90: IL | D90: City of Greenville Drinking Water Treatment Plant Construction | E90: 750000 | F90: Davis, Rodney | H90: H
A91: Environmental Protection Agency | B91: STAG— Drinking Water State Revolving Fund | C91: IL | D91: City of Pana Drinking Water Transmission Main Replacement | E91: 1881600 | F91: Davis, Rodney | H91: H
A92: Environmental Protection Agency | B92: STAG— Drinking Water State Revolving Fund | C92: IL | D92: Sharpsburg & Neighboring Area Water Sys- tem—Rural Water Distribution System Phase 3 | E92: 690750 | F92: Davis, Rodney | H92: H
A93: Environmental Protection Agency | B93: STAG— Drinking Water State Revolving Fund | C93: IL | D93: City of Joliet for a Design and Develop- ment Project | E93: 3452972 | F93: Foster | H93: H
A94: Environmental Protection Agency | B94: STAG— Drinking Water State Revolving Fund | C94: IL | D94: Village of Roberts Emergency Water Infra- structure Needs | E94: 90400 | F94: Kinzinger | H94: H
A95: Environmental Protection Agency | B95: STAG— Drinking Water State Revolving Fund | C95: IL | D95: Village of Manhattan for Well 7 Improve- ments and Radium Reduction Treatment Project | E95: 3452972 | F95: Rush | H95: H
A96: Environmental Protection Agency | B96: STAG— Drinking Water State Revolving Fund | C96: IL | D96: Village of Midlothian for the 149th Street & Pulaski Road Water Main Replace- ment | E96: 1064000 | F96: Rush | H96: H
A97: Environmental Protection Agency | B97: STAG— Drinking Water State Revolving Fund | C97: IL | D97: Village of Skokie for Lead Service Line Re- placement Project | E97: 2000000 | F97: Schakowsky | H97: H
A98: Environmental Protection Agency | B98: STAG— Drinking Water State Revolving Fund | C98: IL | D98: City of Waukegan for a Water Works Im- provement Project | E98: 3452972 | F98: Schneider | H98: H
A99: Environmental Protection Agency | B99: STAG— Drinking Water State Revolving Fund | C99: IL | D99: Village of Oswego for Corrosion Studies | E99: 1800000 | F99: Underwood | H99: H
A100: Environmental Protection Agency | B100: STAG— Drinking Water State Revolving Fund | C100: KS | D100: Kansas City Board of Public Utilities for Aged Water Line Replacement | E100: 10000000 | G100: Moran | H100: S
...

Sheet Sheet1
A1: Agency | B1: Account | C1: State | D1: Project | E1: Amount | F1: House_Requestor | G1: Senate_Requestor | H1: Origination | J1: Sum of Amount | K1: Column Labels
A2: Environmental Protection Agency | B2: STAG— Drinking Water State Revolving Fund | C2: AK | D2: City of Whittier for Well Field Upgrades | E2: 1230000 | G2: Murkowski | H2: S | J2: Row Labels | K2: STAG— Drinking Water State Revolving Fund | L2: STAG—Clean Water State Revolving Fund | M2: (blank) | N2: Grand Total
A3: Environmental Protection Agency | B3: STAG— Drinking Water State Revolving Fund | C3: AK | D3: Chickaloon Village Traditional Council for Community Well in Chickaloon | E3: 250000 | G3: Murkowski | H3: S | J3: AK | K3: 8162000 | L3: 55520000 | N3: 63682000
A4: Environmental Protection Agency | B4: STAG— Drinking Water State Revolving Fund | C4: AK | D4: City and Borough of Yakutat for Waterline Extension Project | E4: 5082000 | G4: Murkowski | H4: S | J4: AL | K4: 1800000 | L4: 7000000 | N4: 8800000
A5: Environmental Protection Agency | B5: STAG— Drinking Water State Revolving Fund | C5: AK | D5: City of Nome for Potable Water Distribution and Wastewater Collection Systems | E5: 1600000 | G5: Murkowski | H5: S | J5: AR | K5: 15050000 | L5: 4660000 | N5: 19710000
A6: Environmental Protection Agency | B6: STAG— Drinking Water State Revolving Fund | C6: AL | D6: Town of Garden City Water System Im- provements | E6: 520000 | F6: Aderholt | H6: H | J6: AZ | K6: 14867361 | L6: 12602350 | N6: 27469711
A7: Environmental Protection Agency | B7: STAG— Drinking Water State Revolving Fund | C7: AL | D7: Mobile County Water, Sewer, and Fire Pro- tection Authority Water Well Project | E7: 1280000 | F7: Carl | H7: H | J7: CA | K7: 74512099 | L7: 74948832 | N7: 149460931
A8: Environmental Protection Agency | B8: STAG— Drinking Water State Revolving Fund | C8: AR | D8: Fulton Waterworks for City of Fulton Water System Delivery | E8: 3050000 | G8: Boozman | H8: S | J8: CNMI | L8: 911302 | N8: 911302
A9: Environmental Protection Agency | B9: STAG— Drinking Water State Revolving Fund | C9: AR | D9: Central Arkansas Water for West Pulaski County Water Delivery | E9: 12000000 | G9: Boozman | H9: S | J9: CO | K9: 13193600 | L9: 2454000 | N9: 15647600
A10: Environmental Protection Agency | B10: STAG— Drinking Water State Revolving Fund | C10: AZ | D10: Bullhead City for New Drinking Water Well Construction Project | E10: 2000000 | G10: Kelly | H10: S | J10: CT | K10: 7863000 | L10: 9225000 | N10: 17088000
A11: Environmental Protection Agency | B11: STAG— Drinking Water State Revolving Fund | C11: AZ | D11: Town of Carefree for Silver Saddle Pres- sure Zone Waterline Improvement Project | E11: 800000 | G11: Kelly | H11: S | J11: DE | K11: 1800000 | L11: 10560000 | N11: 12360000
A12: Environmental Protection Agency | B12: STAG— Drinking Water State Revolving Fund | C12: AZ | D12: City of Page for Water Treatment Plant Ex- pansion Project | E12: 456000 | G12: Kelly | H12: S | J12: FL | K12: 12692972 | L12: 51772327 | N12: 64465299
A13: Environmental Protection Agency | B13: STAG— Drinking Water State Revolving Fund | C13: AZ | D13: City of Douglas for a Supervisory Control and Data Acquisition System | E13: 833285 | F13: Kirkpatrick | G13: Sinema | H13: H | J13: GA | K13: 6436000 | L13: 29398290 | N13: 35834290
A14: Environmental Protection Agency | B14: STAG— Drinking Water State Revolving Fund | C14: AZ | D14: Town of Kearny for a Water Infrastructure Project | E14: 3000000 | F14: O’Halleran | H14: H | J14: HI | K14: 2160000 | L14: 4199000 | N14: 6359000
A15: Environmental Protection Agency | B15: STAG— Drinking Water State Revolving Fund | C15: AZ | D15: Hopi Tribe for a Water Infrastructure Im- provement Project | E15: 1500000 | F15: O’Halleran | G15: Kelly, Sinema | H15: H | J15: IA | L15: 6000000 | N15: 6000000
A16: Environmental Protection Agency | B16: STAG— Drinking Water State Revolving Fund | C16: AZ | D16: Maricopa-Stanfield Irrigation and Drainage District for the Santa Rosa Canal Project | E16: 2846076 | F16: O’Halleran | G16: Kelly, Sinema | H16: H/S | J16: ID | L16: 4560000 | N16: 4560000
A17: Environmental Protection Agency | B17: STAG— Drinking Water State Revolving Fund | C17: AZ | D17: City of Page for New Intake Pipes from Lake Powell | E17: 3432000 | F17: O’Halleran | G17: Sinema | H17: H/S | J17: IL | K17: 25470095 | L17: 22548296 | N17: 48018391
A18: Environmental Protection Agency | B18: STAG— Drinking Water State Revolving Fund | C18: CA | D18: East Palo Alto for East Palo Alto Water In- frastructure Improvements | E18: 800000 | G18: Feinstein | H18: S | J18: KS | K18: 10000000 | L18: 21100000 | N18: 31100000
A19: Environmental Protection Agency | B19: STAG— Drinking Water State Revolving Fund | C19: CA | D19: County of Tulare for Drinking Water Kiosks | E19: 200000 | G19: Feinstein, Padilla | H19: S | J19: KY | K19: 11328000 | L19: 12899000 | N19: 24227000
A20: Environmental Protection Agency | B20: STAG— Drinking Water State Revolving Fund | C20: CA | D20: Woodville Public Utility District for Wood- ville PUD Well No. 4 Replacement | E20: 1150000 | G20: Feinstein, Padilla | H20: S | J20: LA | K20: 4430000 | L20: 10000000 | N20: 14430000
A21: Environmental Protection Agency | B21: STAG— Drinking Water State Revolving Fund | C21: CA | D21: City of Modesto for Grayson Well and Tank Replacement | E21: 1750000 | G21: Feinstein, Padilla | H21: S | J21: MA | K21: 14600894 | L21: 19765800 | N21: 34366694
A22: Environmental Protection Agency | B22: STAG— Drinking Water State Revolving Fund | C22: CA | D22: Allensworth Community Services District for Allensworth Well Solar Array | E22: 150000 | G22: Feinstein, Padilla | H22: S | J22: MD | K22: 5845000 | L22: 10818972 | N22: 16663972
A23: Environmental Protection Agency | B23: STAG— Drinking Water State Revolving Fund | C23: CA | D23: City of Tulare for Water Delivery System | E23: 500000 | G23: Feinstein, Padilla | H23: S | J23: ME | K23: 6084000 | L23: 25829453 | N23: 31913453
A24: Environmental Protection Agency | B24: STAG— Drinking Water State Revolving Fund | C24: CA | D24: City of Dinuba for Well 21 Construction | E24: 1500000 | G24: Padilla | H24: S | J24: MI | K24: 25796772 | L24: 32925944 | N24: 58722716
A25: Environmental Protection Agency | B25: STAG— Drinking Water State Revolving Fund | C25: CA | D25: Carmichael Water District for Aquifer Stor- age and Recharge Well #2 | E25: 2500000 | F25: Bera | H25: H | J25: MN | K25: 17572972 | L25: 12380000 | N25: 29952972
A26: Environmental Protection Agency | B26: STAG— Drinking Water State Revolving Fund | C26: CA | D26: Citrus Heights Water District for the High- land Avenue Well Project | E26: 1500000 | F26: Bera | H26: H | J26: MO | K26: 22240000 | L26: 17401027 | N26: 39641027
A27: Environmental Protection Agency | B27: STAG— Drinking Water State Revolving Fund | C27: CA | D27: Sacramento County for a Regional Con- junctive Use Project | E27: 2800000 | F27: Bera | G27: Padilla | H27: H | J27: MS | K27: 18626424 | L27: 23000000 | N27: 41626424
A28: Environmental Protection Agency | B28: STAG— Drinking Water State Revolving Fund | C28: CA | D28: City of Oxnard for a Water Pipeline Re- placement | E28: 2846400 | F28: Brownley | G28: Feinstein, Padilla | H28: H | J28: NC | K28: 9046872 | L28: 17285839 | N28: 26332711
A29: Environmental Protection Agency | B29: STAG— Drinking Water State Revolving Fund | C29: CA | D29: Cachuma Operation and Maintenance Board for the Lake Cachuma Pumping Facility Project | E29: 500000 | F29: Carbajal | G29: Feinstein | H29: H | J29: NH | K29: 6452972 | L29: 9935000 | N29: 16387972
A30: Environmental Protection Agency | B30: STAG— Drinking Water State Revolving Fund | C30: CA | D30: City of Atwater for the Buhach Road and Gurr Road Utility Extension | E30: 3000000 | F30: Costa | H30: H | J30: NJ | K30: 30896395 | L30: 28126818 | N30: 59023213
A31: Environmental Protection Agency | B31: STAG— Drinking Water State Revolving Fund | C31: CA | D31: Solano Irrigation District for Quail Creek Well Relocation and Associated Convey- ance Facilities | E31: 2824000 | F31: Garamendi | G31: Padilla | H31: H | J31: NM | K31: 4065000 | L31: 13952000 | N31: 18017000
A32: Environmental Protection Agency | B32: STAG— Drinking Water State Revolving Fund | C32: CA | D32: City of Ripon for the SSJID Surface Water Connection Project | E32: 3452972 | F32: Harder (CA) | H32: H | J32: NV | K32: 16106640 | L32: 18269600 | N32: 34376240
A33: Environmental Protection Agency | B33: STAG— Drinking Water State Revolving Fund | C33: CA | D33: Stanislaus County for a Crows Landing Water Wells Project | E33: 3452972 | F33: Harder (CA) | G33: Padilla | H33: H | J33: NY | K33: 46517616 | L33: 63646193 | N33: 110163809
A34: Environmental Protection Agency | B34: STAG— Drinking Water State Revolving Fund | C34: CA | D34: Valley Center Municipal Water District Lilac Road Pipeline Replacement Project | E34: 3060000 | F34: Issa | G34: Feinstein, Padilla | H34: H | J34: OH | K34: 11428540 | L34: 36334946 | N34: 47763486
A35: Environmental Protection Agency | B35: STAG— Drinking Water State Revolving Fund | C35: CA | D35: Borrego Water District—Borrego Spring Road Transmission Main and Sun Gold Pipeline Replacement Projects | E35: 3392667 | F35: Issa | G35: Padilla | H35: H | J35: OK | K35: 32203281 | L35: 10936000 | N35: 43139281
A36: Environmental Protection Agency | B36: STAG— Drinking Water State Revolving Fund | C36: CA | D36: Orange County Water District PFAS Groundwater Treatment Project | E36: 5000000 | F36: Kim (CA) | G36: Padilla | H36: H | J36: OR | K36: 20522000 | L36: 15952950 | N36: 36474950
A37: Environmental Protection Agency | B37: STAG— Drinking Water State Revolving Fund | C37: CA | D37: Placer County Water Agency Alta Loop Pipeline Project | E37: 1000000 | F37: LaMalfa | H37: H | J37: PA | K37: 5040400 | L37: 28517287 | N37: 33557687
A38: Environmental Protection Agency | B38: STAG— Drinking Water State Revolving Fund | C38: CA | D38: City of Sacramento for the Shasta Ground- water Well Project | E38: 3452972 | F38: Matsui | H38: H | J38: RI | K38: 5000000 | L38: 10828000 | N38: 15828000
A39: Environmental Protection Agency | B39: STAG— Drinking Water State Revolving Fund | C39: CA | D39: City of Azusa for Aspan Well Treatment and Rehabilitation | E39: 2500000 | F39: Napolitano | H39: H | J39: SC | K39: 9900000 | L39: 19523000 | N39: 29423000
A40: Environmental Protection Agency | B40: STAG— Drinking Water State Revolving Fund | C40: CA | D40: City of Salinas for the Castroville Seawater Intrusion Project | E40: 900000 | F40: Panetta | G40: Feinstein, Padilla | H40: H | J40: TN | K40: 5800000 | L40: 4122800 | N40: 9922800
A41: Environmental Protection Agency | B41: STAG— Drinking Water State Revolving Fund | C41: CA | D41: Soquel Creek Water District for a Water Reliability Improvement Project | E41: 1416000 | F41: Panetta | G41: Padilla | H41: H | J41: TX | K41: 4500000 | L41: 36401584 | N41: 40901584
A42: Environmental Protection Agency | B42: STAG— Drinking Water State Revolving Fund | C42: CA | D42: City of Hemet for the Oakland and Santa Fe Water Main Replacement Project | E42: 1200000 | F42: Ruiz | H42: H | J42: UT | K42: 11876640 | L42: 12500000 | N42: 24376640
A43: Environmental Protection Agency | B43: STAG— Drinking Water State Revolving Fund | C43: CA | D43: Coachella Valley Water District for a Water Consolidation Project | E43: 3452972 | F43: Ruiz | G43: Feinstein, Padilla | H43: H | J43: VA | K43: 6452972 | L43: 6760000 | N43: 13212972
A44: Environmental Protection Agency | B44: STAG— Drinking Water State Revolving Fund | C44: CA | D44: City of Santa Fe Springs for Water Well No. 12 Assessment and Treatment | E44: 2200000 | F44: Sanchez | H44: H | J44: VT | K44: 3685000 | L44: 1920000 | N44: 5605000
A45: Environmental Protection Agency | B45: STAG— Drinking Water State Revolving Fund | C45: CA | D45: Water Replenishment District of Southern California for Five Groundwater Well Projects | E45: 2500000 | F45: Sanchez | G45: Padilla | H45: H | J45: WA | K45: 15167972 | L45: 16054632 | N45: 31222604
A46: Environmental Protection Agency | B46: STAG— Drinking Water State Revolving Fund | C46: CA | D46: City of Pleasanton for a PFAS Treatment and Well Rehabilitation Project | E46: 2000000 | F46: Swalwell | G46: Feinstein, Padilla | H46: H | J46: WI | K46: 14452972 | L46: 4423400 | N46: 18876372
A47: Environmental Protection Agency | B47: STAG— Drinking Water State Revolving Fund | C47: CA | D47: Eastern Municipal Water District for the Well 56 & 57 PFAS Removal Project | E47: 3452972 | F47: Takano | G47: Feinstein, Padilla | H47: H | J47: WV | K47: 29609438 | L47: 25139000 | N47: 54748438
A48: Environmental Protection Agency | B48: STAG— Drinking Water State Revolving Fund | C48: CA | D48: City of Pomona for Groundwater Treatment R34 | E48: 1600000 | F48: Torres (CA) | H48: H | J48: (blank)
A49: Environmental Protection Agency | B49: STAG— Drinking Water State Revolving Fund | C49: CA | D49: City of Chino for a Treatment Plant Groundwater Wells 4 & 6 Project | E49: 2000000 | F49: Torres (CA) | H49: H | J49: Grand Total | K49: 609255899 | L49: 863108642 | N49: 1472364541
A50: Environmental Protection Agency | B50: STAG— Drinking Water State Revolving Fund | C50: CA | D50: City of Fowler New Well and System Inter- connection for Drought Resiliency Project | E50: 3005200 | F50: Valadao | H50: H
A51: Environmental Protection Agency | B51: STAG— Drinking Water State Revolving Fund | C51: CA | D51: City of Inglewood for a Water Main Re- placement Project | E51: 3452972 | F51: Waters | H51: H
A52: Environmental Protection Agency | B52: STAG— Drinking Water State Revolving Fund | C52: CO | D52: Beulah Water Works District for Raw Water Storage | E52: 380000 | G52: Bennet, Hickenlooper | H52: S
A53: Environmental Protection Agency | B53: STAG— Drinking Water State Revolving Fund | C53: CO | D53: Town of Naturita for Wastewater Treatment Plant Lagoon Upgrade and Collection System | E53: 1250000 | G53: Bennet, Hickenlooper | H53: S
A54: Environmental Protection Agency | B54: STAG— Drinking Water State Revolving Fund | C54: CO | D54: City of Delta for North Delta Water Line Replacement | E54: 380000 | G54: Bennet, Hickenlooper | H54: S
A55: Environmental Protection Agency | B55: STAG— Drinking Water State Revolving Fund | C55: CO | D55: City of Trinidad for a Drinking Water Infra- structure Project | E55: 1149000 | G55: Hickenlooper | H55: S
A56: Environmental Protection Agency | B56: STAG— Drinking Water State Revolving Fund | C56: CO | D56: Town of Cheraw for a Regional Consolida- tion Project | E56: 1625000 | G56: Hickenlooper | H56: S
A57: Environmental Protection Agency | B57: STAG— Drinking Water State Revolving Fund | C57: CO | D57: Town of Superior for Granular Activated Carbon System at Water Treatment Plant | E57: 1280000 | G57: Hickenlooper | H57: S
A58: Environmental Protection Agency | B58: STAG— Drinking Water State Revolving Fund | C58: CO | D58: City of Aurora for a Waterline Replacement Program | E58: 2800000 | F58: Crow | G58: Bennet, Hickenlooper | H58: H
A59: Environmental Protection Agency | B59: STAG— Drinking Water State Revolving Fund | C59: CO | D59: Town of Minturn for a Water Treatment Plant | E59: 2000000 | F59: Neguse | G59: Bennet | H59: H
A60: Environmental Protection Agency | B60: STAG— Drinking Water State Revolving Fund | C60: CO | D60: City of Northglenn for Water Treatment Plant Improvements | E60: 2329600 | F60: Perlmutter | G60: Hickenlooper | H60: H
A61: Environmental Protection Agency | B61: STAG— Drinking Water State Revolving Fund | C61: CT | D61: School Hill Water Association for Clean Water for the School Hill Association | E61: 1200000 | G61: Blumenthal, Murphy | H61: S
A62: Environmental Protection Agency | B62: STAG— Drinking Water State Revolving Fund | C62: CT | D62: The South Central Regional Water Authority for Lake Gaillard Water Treatment Plant HVAC and Electrical Improvements | E62: 2647000 | G62: Blumenthal, Murphy | H62: S
A63: Environmental Protection Agency | B63: STAG— Drinking Water State Revolving Fund | C63: CT | D63: The South Central Regional Water Authority for Seymour Well Treatment Facility Generator Replacement | E63: 716000 | G63: Blumenthal, Murphy | H63: S
A64: Environmental Protection Agency | B64: STAG— Drinking Water State Revolving Fund | C64: CT | D64: The Metropolitan District Commission for Northeast Transmission Water Main | E64: 2500000 | G64: Blumenthal, Murphy | H64: S
A65: Environmental Protection Agency | B65: STAG— Drinking Water State Revolving Fund | C65: CT | D65: Norwich Public Utilities for Poquetanuck Cove Crossing Water Interconnect | E65: 800000 | G65: Blumenthal, Murphy | H65: S
A66: Environmental Protection Agency | B66: STAG— Drinking Water State Revolving Fund | C66: DE | D66: City of Dover for Water Main Extension and New Well | E66: 1800000 | G66: Carper, Coons | H66: S
A67: Environmental Protection Agency | B67: STAG— Drinking Water State Revolving Fund | C67: FL | D67: City of Fort Myers Water Treatment Expan- sion Plan | E67: 2500000 | F67: Donalds | H67: H
A68: Environmental Protection Agency | B68: STAG— Drinking Water State Revolving Fund | C68: FL | D68: Town of Lantana for a Water Main Repair Project | E68: 1200000 | F68: Frankel, Lois | H68: H
A69: Environmental Protection Agency | B69: STAG— Drinking Water State Revolving Fund | C69: FL | D69: Village of Pinecrest Waterline Lateral Con- nection Project | E69: 640000 | F69: Salazar | H69: H
A70: Environmental Protection Agency | B70: STAG— Drinking Water State Revolving Fund | C70: FL | D70: DeSoto County for the Restoration of Shoreline Off the Peace River in DeSoto County | E70: 2500000 | F70: Steube | H70: H
A71: Environmental Protection Agency | B71: STAG— Drinking Water State Revolving Fund | C71: FL | D71: Lee County for the North Lee County Wellfield Expansion Project | E71: 2400000 | F71: Steube | H71: H
A72: Environmental Protection Agency | B72: STAG— Drinking Water State Revolving Fund | C72: FL | D72: City of Hollywood for Membrane Softening Drinking Water Upgrades | E72: 3452972 | F72: Wasserman Schultz | H72: H
A73: Environmental Protection Agency | B73: STAG— Drinking Water State Revolving Fund | C73: GA | D73: City of Byron for Walker Road Drinking Water Improvement | E73: 651000 | G73: Ossoff | H73: S
A74: Environmental Protection Agency | B74: STAG— Drinking Water State Revolving Fund | C74: GA | D74: Augusta-Richmond County for Water Line Evaluation | E74: 1000000 | G74: Warnock | H74: S
A75: Environmental Protection Agency | B75: STAG— Drinking Water State Revolving Fund | C75: GA | D75: City of Keysville for Water Supply and Water Source Lines | E75: 197000 | G75: Warnock | H75: S
A76: Environmental Protection Agency | B76: STAG— Drinking Water State Revolving Fund | C76: GA | D76: Gwinnett County for Replacement and Up- grade of Aged Water Distribution Mains | E76: 2988000 | F76: Bourdeaux | H76: H
A77: Environmental Protection Agency | B77: STAG— Drinking Water State Revolving Fund | C77: GA | D77: City of East Point for a Water Main Up- grade Project | E77: 1600000 | F77: Williams (GA) | G77: Warnock | H77: H
A78: Environmental Protection Agency | B78: STAG— Drinking Water State Revolving Fund | C78: HI | D78: County of Hawai’i for North Kona Deep Well | E78: 2080000 | G78: Hirono, Schatz | H78: S
A79: Environmental Protection Agency | B79: STAG— Drinking Water State Revolving Fund | C79: HI | D79: County of Hawai’i for Large Water Meter Replacement | E79: 80000 | G79: Hirono, Schatz | H79: S
A80: Environmental Protection Agency | B80: STAG— Drinking Water State Revolving Fund | C80: IL | D80: City of Chicago for Daycare Lead Service Line Replacement | E80: 1000000 | G80: Duckworth | H80: S
A81: Environmental Protection Agency | B81: STAG— Drinking Water State Revolving Fund | C81: IL | D81: City of Edwardsville for Cass Avenue Water Main Replacement | E81: 500000 | G81: Durbin | H81: S
A82: Environmental Protection Agency | B82: STAG— Drinking Water State Revolving Fund | C82: IL | D82: Village of Ivesdale for Water Main Im- provements | E82: 250000 | G82: Durbin | H82: S
A83: Environmental Protection Agency | B83: STAG— Drinking Water State Revolving Fund | C83: IL | D83: Villages of Bedford Park & Lemont for Water Connection Project | E83: 500000 | G83: Durbin | H83: S
A84: Environmental Protection Agency | B84: STAG— Drinking Water State Revolving Fund | C84: IL | D84: City of Centralia for Water Line Replace- ment | E84: 500000 | G84: Durbin | H84: S
A85: Environmental Protection Agency | B85: STAG— Drinking Water State Revolving Fund | C85: IL | D85: City of Quincy for Lead Service Line Re- placement | E85: 400000 | G85: Durbin | H85: S
A86: Environmental Protection Agency | B86: STAG— Drinking Water State Revolving Fund | C86: IL | D86: DuPage County for York Township Drinking Water Project | E86: 300000 | G86: Durbin | H86: S
A87: Environmental Protection Agency | B87: STAG— Drinking Water State Revolving Fund | C87: IL | D87: City of Waukegan for Lead Service Line Replacement | E87: 500000 | G87: Durbin | H87: S
A88: Environmental Protection Agency | B88: STAG— Drinking Water State Revolving Fund | C88: IL | D88: City of Lewistown for a Municipal Water Supply Project | E88: 600000 | F88: Bustos | H88: H
A89: Environmental Protection Agency | B89: STAG— Drinking Water State Revolving Fund | C89: IL | D89: City of Litchfield Drinking Water Distribu- tion System Improvements Phase I & II | E89: 2284429 | F89: Davis, Rodney | H89: H
A90: Environmental Protection Agency | B90: STAG— Drinking Water State Revolving Fund | C90: IL | D90: City of Greenville Drinking Water Treatment Plant Construction | E90: 750000 | F90: Davis, Rodney | H90: H
A91: Environmental Protection Agency | B91: STAG— Drinking Water State Revolving Fund | C91: IL | D91: City of Pana Drinking Water Transmission Main Replacement | E91: 1881600 | F91: Davis, Rodney | H91: H
A92: Environmental Protection Agency | B92: STAG— Drinking Water State Revolving Fund | C92: IL | D92: Sharpsburg & Neighboring Area Water Sys- tem—Rural Water Distribution System Phase 3 | E92: 690750 | F92: Davis, Rodney | H92: H
A93: Environmental Protection Agency | B93: STAG— Drinking Water State Revolving Fund | C93: IL | D93: City of Joliet for a Design and Develop- ment Project | E93: 3452972 | F93: Foster | H93: H
A94: Environmental Protection Agency | B94: STAG— Drinking Water State Revolving Fund | C94: IL | D94: Village of Roberts Emergency Water Infra- structure Needs | E94: 90400 | F94: Kinzinger | H94: H
A95: Environmental Protection Agency | B95: STAG— Drinking Water State Revolving Fund | C95: IL | D95: Village of Manhattan for Well 7 Improve- ments and Radium Reduction Treatment Project | E95: 3452972 | F95: Rush | H95: H
A96: Environmental Protection Agency | B96: STAG— Drinking Water State Revolving Fund | C96: IL | D96: Village of Midlothian for the 149th Street & Pulaski Road Water Main Replace- ment | E96: 1064000 | F96: Rush | H96: H
A97: Environmental Protection Agency | B97: STAG— Drinking Water State Revolving Fund | C97: IL | D97: Village of Skokie for Lead Service Line Re- placement Project | E97: 2000000 | F97: Schakowsky | H97: H
A98: Environmental Protection Agency | B98: STAG— Drinking Water State Revolving Fund | C98: IL | D98: City of Waukegan for a Water Works Im- provement Project | E98: 3452972 | F98: Schneider | H98: H
A99: Environmental Protection Agency | B99: STAG— Drinking Water State Revolving Fund | C99: IL | D99: Village of Oswego for Corrosion Studies | E99: 1800000 | F99: Underwood | H99: H
A100: Environmental Protection Agency | B100: STAG— Drinking Water State Revolving Fund | C100: KS | D100: Kansas City Board of Public Utilities for Aged Water Line Replacement | E100: 10000000 | G100: Moran | H100: S
...

Sheet CW_24_cap
A1: state | B1: allotment | C1: pct
A2: Alabama | B2: 9221000 | C2: =B2/tot_allotment!$E$3 -> 0.011181795
A3: Alaska | B3: 4935000 | C3: =B3/tot_allotment!$E$3 -> 0.0059844005
A4: Arizona | B4: 5570000 | C4: =B4/tot_allotment!$E$3 -> 0.0067544298
A5: Arkansas | B5: 5394000 | C5: =B5/tot_allotment!$E$3 -> 0.0065410044
A6: California | B6: 58976000 | C6: =B6/tot_allotment!$E$3 -> 0.071516921
A7: Colorado | B7: 6596000 | C7: =B7/tot_allotment!$E$3 -> 0.007998603
A8: Connecticut | B8: 10102000 | C8: =B8/tot_allotment!$E$3 -> 0.012250135
A9: Delaware | B9: 4048000 | C9: =B9/tot_allotment!$E$3 -> 0.0049087849
A10: Florida | B10: 27835000 | C10: =B10/tot_allotment!$E$3 -> 0.033753959
A11: Georgia | B11: 13942000 | C11: =B11/tot_allotment!$E$3 -> 0.016906689
A12: Hawaii | B12: 6387000 | C12: =B12/tot_allotment!$E$3 -> 0.0077451603
A13: Idaho | B13: 4048000 | C13: =B13/tot_allotment!$E$3 -> 0.0049087849
... A52: Wyoming | B52: 4048000 | C52: =B52/tot_allotment!$E$3 -> 0.0049087849

Sheet DW_24_cap
A1: state | B1: allotment | C1: pct
A2: Alabama | B2: 8229000 | C2: 0.0177
A3: Alaska | B3: 4661000 | C3: 0.01
A4: Arizona | B4: 8153000 | C4: 0.0175
A5: Arkansas | B5: 5580000 | C5: 0.012
A6: California | B6: 50283000 | C6: 0.1079
A7: Colorado | B7: 8164000 | C7: 0.0175
A8: Connecticut | B8: 4661000 | C8: 0.01
A9: Delaware | B9: 4661000 | C9: 0.01
A10: Florida | B10: 16819000 | C10: 0.0361
A11: Georgia | B11: 12637000 | C11: 0.0271
A12: Hawaii | B12: 4661000 | C12: 0.01
A13: Idaho | B13: 4661000 | C13: 0.01
... A52: Wyoming | B52: 4661000 | C52: 0.01

Sheet cds_24
A1: Agency | B1: Account | C1: State | D1: Project | E1: Amount | F1: House_Requestor | G1: Senate_Requestor | H1: Origination
A2: Environmental Protection Agency | B2: STAG—Clean Water State Revolving Fund | C2: AL | D2: City of Cullman for Sanitary Sewer Im- provements | E2: 4250000 | F2: Aderholt | H2: H
A3: Environmental Protection Agency | B3: STAG—Clean Water State Revolving Fund | C3: AL | D3: City of Priceville for Sanitary Sewer Im- provements | E3: 1750000 | F3: Strong | H3: H
A4: Environmental Protection Agency | B4: STAG—Clean Water State Revolving Fund | C4: AZ | D4: City of Tempe for Recharge Wells Pipelines | E4: 959752 | F4: Stanton | G4: Sinema | H4: H
A5: Environmental Protection Agency | B5: STAG—Clean Water State Revolving Fund | C5: AZ | D5: City of Tolleson for Wastewater Digester Rehabilitation Project | E5: 959752 | F5: Gallego | G5: Sinema | H5: H
A6: Environmental Protection Agency | B6: STAG—Clean Water State Revolving Fund | C6: AZ | D6: Tucson Water for Water Recharge Expan- sion Project | E6: 1250000 | F6: Ciscomani | G6: Sinema | H6: H
A7: Environmental Protection Agency | B7: STAG—Clean Water State Revolving Fund | C7: CA | D7: Arvin-Edison Water Storage District for Water Pipeline Project | E7: 3250000 | F7: Valadao | H7: H
A8: Environmental Protection Agency | B8: STAG—Clean Water State Revolving Fund | C8: CA | D8: Big Bear Area Regional Wastewater Agency for Water Reuse Project | E8: 1000000 | F8: Obernolte | G8: Padilla | H8: H
A9: Environmental Protection Agency | B9: STAG—Clean Water State Revolving Fund | C9: CA | D9: California Department of Parks and Recre- ation, Angeles Division for Taylor Yard Stormwater Project | E9: 959752 | F9: Gomez | H9: H
A10: Environmental Protection Agency | B10: STAG—Clean Water State Revolving Fund | C10: CA | D10: City of Adelanto for Water and Wastewater Infrastructure Improvements | E10: 750000 | F10: Obernolte | H10: H
A11: Environmental Protection Agency | B11: STAG—Clean Water State Revolving Fund | C11: CA | D11: City of Compton for Pearl Avenue Sewer Replacement Project | E11: 959752 | F11: Waters | G11: Feinstein, Padilla | H11: H
A12: Environmental Protection Agency | B12: STAG—Clean Water State Revolving Fund | C12: CA | D12: City of Daly City for Vista Grande Drainage Basin Improvement Project | E12: 959752 | F12: Mullin | H12: H
A13: Environmental Protection Agency | B13: STAG—Clean Water State Revolving Fund | C13: CA | D13: City of Del Mar for Stormwater and Sewer Infrastructure Improvement Project | E13: 959752 | F13: Levin | G13: Padilla | H13: H
A14: Environmental Protection Agency | B14: STAG—Clean Water State Revolving Fund | C14: CA | D14: City of Dinuba for Sewer Improvements | E14: 959752 | F14: Costa | G14: Padilla | H14: H
A15: Environmental Protection Agency | B15: STAG—Clean Water State Revolving Fund | C15: CA | D15: City of Madera for Sewer Trunk Main Project | E15: 1000000 | F15: Duarte | H15: H
A16: Environmental Protection Agency | B16: STAG—Clean Water State Revolving Fund | C16: CA | D16: City of Madera for Storm Drain Pipeline Replacement | E16: 1000000 | F16: Duarte | G16: Padilla | H16: H
A17: Environmental Protection Agency | B17: STAG—Clean Water State Revolving Fund | C17: CA | D17: City of Oakland for Lake Merritt Healthy Lake Initiative | E17: 959757 | F17: Lee (CA) | G17: Feinstein, Padilla | H17: H
A18: Environmental Protection Agency | B18: STAG—Clean Water State Revolving Fund | C18: CA | D18: City of Pleasanton for South Livermore Sewer Expansion Project | E18: 959752 | F18: Swalwell | H18: H
A19: Environmental Protection Agency | B19: STAG—Clean Water State Revolving Fund | C19: CA | D19: City of Rio Vista for Reclaimed Water Sys- tem Completion Project (Purple Piping) | E19: 959752 | F19: Thompson (CA) | H19: H
A20: Environmental Protection Agency | B20: STAG—Clean Water State Revolving Fund | C20: CA | D20: City of Salinas for Wastewater Treatment Facility Project | E20: 959752 | F20: Lofgren | G20: Padilla | H20: H
A21: Environmental Protection Agency | B21: STAG—Clean Water State Revolving Fund | C21: CA | D21: City of San Diego for Harbor Drive Pump Station 1 and 2 Project | E21: 959752 | F21: Peters | H21: H
A22: Environmental Protection Agency | B22: STAG—Clean Water State Revolving Fund | C22: CA | D22: City of Santa Maria for Storm Drainage Improvements Project | E22: 959752 | F22: Carbajal | G22: Feinstein, Padilla | H22: H
A23: Environmental Protection Agency | B23: STAG—Clean Water State Revolving Fund | C23: CA | D23: City of Stockton for Diamond Sewer Upsizing Project | E23: 959757 | F23: Harder | H23: H
A24: Environmental Protection Agency | B24: STAG—Clean Water State Revolving Fund | C24: CA | D24: City of Thousand Oaks for Stormwater Capture and Diversion Project | E24: 959752 | F24: Brownley | H24: H
A25: Environmental Protection Agency | B25: STAG—Clean Water State Revolving Fund | C25: CA | D25: City of Tulare for Traver Sewer Project | E25: 750000 | F25: Costa | H25: H
A26: Environmental Protection Agency | B26: STAG—Clean Water State Revolving Fund | C26: CA | D26: City of Turlock for Sewer Extension Project | E26: 1200000 | F26: Duarte | G26: Padilla | H26: H
A27: Environmental Protection Agency | B27: STAG—Clean Water State Revolving Fund | C27: CA | D27: City of Turlock for Stormwater Infrastruc- ture | E27: 1000000 | F27: Duarte | G27: Feinstein, Padilla | H27: H
A28: Environmental Protection Agency | B28: STAG—Clean Water State Revolving Fund | C28: CA | D28: City of Twentynine Palms for Wastewater Improvements | E28: 1000000 | F28: Obernolte | G28: Feinstein, Padilla | H28: H
A29: Environmental Protection Agency | B29: STAG—Clean Water State Revolving Fund | C29: CA | D29: City of Watsonville for Wastewater Treat- ment Facility | E29: 959752 | F29: Lofgren | H29: H
A30: Environmental Protection Agency | B30: STAG—Clean Water State Revolving Fund | C30: CA | D30: City of Yucaipa for Stormwater Infrastruc- ture Project | E30: 1750000 | F30: Obernolte | G30: Padilla | H30: H
A31: Environmental Protection Agency | B31: STAG—Clean Water State Revolving Fund | C31: CA | D31: County of Los Angeles for Rio Hondo Res- toration Project | E31: 959752 | F31: Chu | H31: H
A32: Environmental Protection Agency | B32: STAG—Clean Water State Revolving Fund | C32: CA | D32: County of Orange for Poche Beach Water Reclamation Project | E32: 959752 | F32: Levin | H32: H
A33: Environmental Protection Agency | B33: STAG—Clean Water State Revolving Fund | C33: CA | D33: Culver City for Stormwater Diversion | E33: 959752 | F33: Lieu | H33: H
A34: Environmental Protection Agency | B34: STAG—Clean Water State Revolving Fund | C34: CA | D34: Eastern Municipal Water District for Puri- fied Water Replenishment Project | E34: 959752 | F34: Takano | H34: H
A35: Environmental Protection Agency | B35: STAG—Clean Water State Revolving Fund | C35: CA | D35: Eastern Municipal Water District for Recy- cled Water Pipeline Construction | E35: 638540 | F35: Issa | H35: H
A36: Environmental Protection Agency | B36: STAG—Clean Water State Revolving Fund | C36: CA | D36: Goleta County for Wastewater Reuse Project | E36: 773870 | F36: Carbajal | H36: H
A37: Environmental Protection Agency | B37: STAG—Clean Water State Revolving Fund | C37: CA | D37: Los Angeles County Public Works for Stormwater Infrastructure Improvements | E37: 1050000 | F37: Garcia, Mike (CA) | H37: H
A38: Environmental Protection Agency | B38: STAG—Clean Water State Revolving Fund | C38: CA | D38: Mojave Water Agency for Stormwater Cap- ture and Recharge | E38: 1750000 | F38: Obernolte | G38: Feinstein, Padilla | H38: H
A39: Environmental Protection Agency | B39: STAG—Clean Water State Revolving Fund | C39: CA | D39: Pittsburg Power Company for Water Treat- ment Plant Fuel Cell Project | E39: 959752 | F39: Garamendi | H39: H
A40: Environmental Protection Agency | B40: STAG—Clean Water State Revolving Fund | C40: CA | D40: Port of Redwood City for Storm Water and Clean Water Improvement | E40: 700000 | F40: Mullin | G40: Feinstein, Padilla | H40: H
A41: Environmental Protection Agency | B41: STAG—Clean Water State Revolving Fund | C41: CA | D41: Rainbow Municipal Water District for Lift Station and Sewer Improvements | E41: 1596762 | F41: Issa | H41: H
A42: Environmental Protection Agency | B42: STAG—Clean Water State Revolving Fund | C42: CA | D42: Sacramento Area Sewer District for Septic to Sewer Collection | E42: 959752 | F42: Matsui | H42: H
A43: Environmental Protection Agency | B43: STAG—Clean Water State Revolving Fund | C43: CA | D43: San Bernardino County Flood Control Dis- trict for Stormwater Infrastructure Project | E43: 1750000 | F43: Obernolte | H43: H
A44: Environmental Protection Agency | B44: STAG—Clean Water State Revolving Fund | C44: CA | D44: San Bernardino County Flood Control Dis- trict for Water Infrastructure Project | E44: 1000000 | F44: Obernolte | H44: H
A45: Environmental Protection Agency | B45: STAG—Clean Water State Revolving Fund | C45: CA | D45: San Bernardino County for Bohnert Sewer Project | E45: 959757 | F45: Aguilar | H45: H
A46: Environmental Protection Agency | B46: STAG—Clean Water State Revolving Fund | C46: CA | D46: San Bernardino County for Septic-to-Sewer Conversion Project—Phase 1 | E46: 959757 | F46: Torres (CA) | H46: H
A47: Environmental Protection Agency | B47: STAG—Clean Water State Revolving Fund | C47: CA | D47: Santa Margarita Water District for Brine Line Construction | E47: 1000000 | F47: Kim (CA) | H47: H
A48: Environmental Protection Agency | B48: STAG—Clean Water State Revolving Fund | C48: CA | D48: Sewerage Commission, Oroville Region for Wastewater Treatment Plant Upgrade | E48: 2000000 | F48: LaMalfa | H48: H
A49: Environmental Protection Agency | B49: STAG—Clean Water State Revolving Fund | C49: CA | D49: Town of Paradise for Sewer Regionalization Connection | E49: 1750000 | F49: LaMalfa | G49: Feinstein | H49: H
A50: Environmental Protection Agency | B50: STAG—Clean Water State Revolving Fund | C50: CA | D50: University of California, Davis for In-Lake Water Treatment System at Clear Lake | E50: 959752 | F50: Thompson (CA) | H50: H
A51: Environmental Protection Agency | B51: STAG—Clean Water State Revolving Fund | C51: CA | D51: Western Riverside County Regional Waste- water Authority for Recycled Water Booster Station and Reservoir Project | E51: 3000000 | F51: Calvert | H51: H
A52: Environmental Protection Agency | B52: STAG—Clean Water State Revolving Fund | C52: CO | D52: Town of Gypsum for Wastewater Infra- structure Project | E52: 959752 | F52: Neguse | G52: Bennet, Hickenlooper | H52: H
A53: Environmental Protection Agency | B53: STAG—Clean Water State Revolving Fund | C53: CT | D53: City of New Britain for Fresh Line Up- grades for Streets and Houses | E53: 959752 | F53: Hayes | G53: Murphy, Blumenthal | H53: H
A54: Environmental Protection Agency | B54: STAG—Clean Water State Revolving Fund | C54: CT | D54: City of Norwalk for Lockwood & Heather Lane Drainage Improvements | E54: 959752 | F54: Himes | G54: Murphy, Blumenthal | H54: H
A55: Environmental Protection Agency | B55: STAG—Clean Water State Revolving Fund | C55: CT | D55: City of Stamford for Stormwater Infrastruc- ture Improvements | E55: 959752 | F55: Himes | G55: Murphy, Blumenthal | H55: H
A56: Environmental Protection Agency | B56: STAG—Clean Water State Revolving Fund | C56: CT | D56: Plymouth Water Pollution Control Authority for a Phosphorous Reduction Project | E56: 959752 | F56: Hayes | G56: Murphy, Blumenthal | H56: H
A57: Environmental Protection Agency | B57: STAG—Clean Water State Revolving Fund | C57: CT | D57: Town of Suffield for Stony Brook Inter- ceptor Rehabilitation Project | E57: 959752 | F57: Courtney | G57: Murphy, Blumenthal | H57: H
A58: Environmental Protection Agency | B58: STAG—Clean Water State Revolving Fund | C58: FL | D58: Brevard County for Septic System Up- grades | E58: 1440000 | F58: Posey | H58: H
A59: Environmental Protection Agency | B59: STAG—Clean Water State Revolving Fund | C59: FL | D59: Brevard County for Water Restoration Project | E59: 1750000 | F59: Posey | H59: H
A60: Environmental Protection Agency | B60: STAG—Clean Water State Revolving Fund | C60: FL | D60: Citrus County for Sanitary Sewer System Construction | E60: 1266667 | F60: Bilirakis | H60: H
A61: Environmental Protection Agency | B61: STAG—Clean Water State Revolving Fund | C61: FL | D61: City of Cape Coral for Septic to Sewer Conversion and Utilities Extension | E61: 1000000 | F61: Donalds | H61: H
A62: Environmental Protection Agency | B62: STAG—Clean Water State Revolving Fund | C62: FL | D62: City of Clewiston for Wastewater Treatment Plant Improvements and Expansion | E62: 2094724 | F62: Franklin | H62: H
A63: Environmental Protection Agency | B63: STAG—Clean Water State Revolving Fund | C63: FL | D63: City of Cooper City for Gravity Sewer Line Rehabilitation / Inflow and Infiltration Correction Project | E63: 959757 | F63: Wasserman Schultz | H63: H
A64: Environmental Protection Agency | B64: STAG—Clean Water State Revolving Fund | C64: FL | D64: City of Gulfport for Sanitary Sewer Repair Project | E64: 2545457 | F64: Luna | H64: H
A65: Environmental Protection Agency | B65: STAG—Clean Water State Revolving Fund | C65: FL | D65: City of Inverness for Master Lift Station Resiliency Project | E65: 1266667 | F65: Bilirakis | H65: H
A66: Environmental Protection Agency | B66: STAG—Clean Water State Revolving Fund | C66: FL | D66: City of Orlando for Stormwater Manage- ment Improvements | E66: 959752 | F66: Frost | H66: H
A67: Environmental Protection Agency | B67: STAG—Clean Water State Revolving Fund | C67: FL | D67: City of Orlando for Ventura and Lake Roper Stormwater Improvement Project | E67: 959752 | F67: Soto | H67: H
A68: Environmental Protection Agency | B68: STAG—Clean Water State Revolving Fund | C68: FL | D68: City of Port St. Lucie for Water Quality Im- provement Project | E68: 1000000 | F68: Mast | H68: H
A69: Environmental Protection Agency | B69: STAG—Clean Water State Revolving Fund | C69: FL | D69: City of Sanford for Watermain and Forcemain Installation Project | E69: 2000000 | F69: Mills | H69: H
... A90: Environmental Protection Agency | B90: STAG—Clean Water State Revolving Fund | C90: GA | D90: Effingham County Board of Commissioners for Sewer Force Main Construction | E90: 1750000 | F90: Carter (GA) | H90: H
A91: Environmental Protection Agency | B91: STAG—Clean Water State Revolving Fund | C91: GA | D91: Rockdale County for Almand Branch Waste Water Treatment Project | E91: 959752 | F91: Johnson (GA) | G91: Warnock | H91: H
A92: Environmental Protection Agency | B92: STAG—Clean Water State Revolving Fund | C92: GA | D92: Rockdale County for Honey and Scott Creek Pump Stations and Force Mains Project | E92: 959752 | F92: Johnson (GA) | G92: Warnock | H92: H
A93: Environmental Protection Agency | B93: STAG—Clean Water State Revolving Fund | C93: GA | D93: Rockdale County for River Street Water and Sewer Improvements | E93: 959752 | F93: Johnson (GA) | G93: Warnock | H93: H
A94: Environmental Protection Agency | B94: STAG—Clean Water State Revolving Fund | C94: GA | D94: Rockdale County for Salem Lake Pump Station Replacement Project | E94: 959752 | F94: Johnson (GA) | G94: Ossoff, Warnock | H94: H
A95: Environmental Protection Agency | B95: STAG—Clean Water State Revolving Fund | C95: GA | D95: Whitfield County Board of Commissioners for Sewer Expansion | E95: 1000000 | F95: Greene | G95: Ossoff, Warnock | H95: H
A96: Environmental Protection Agency | B96: STAG—Clean Water State Revolving Fund | C96: IA | D96: City of Fort Madison for Combined Sewer Separation Project | E96: 1750000 | F96: Miller-Meeks | H96: H
A97: Environmental Protection Agency | B97: STAG—Clean Water State Revolving Fund | C97: IA | D97: City of Morning Sun for Wastewater Treat- ment Project | E97: 1000000 | F97: Miller-Meeks | H97: H
A98: Environmental Protection Agency | B98: STAG—Clean Water State Revolving Fund | C98: IA | D98: City of Winfield for Wastewater Treatment Plant | E98: 1000000 | F98: Miller-Meeks | H98: H
A99: Environmental Protection Agency | B99: STAG—Clean Water State Revolving Fund | C99: ID | D99: City of Pocatello for Septic Municipal Con- nection | E99: 1750000 | F99: Simpson | H99: H
A100: Environmental Protection Agency | B100: STAG—Clean Water State Revolving Fund | C100: ID | D100: City of Rexburg for Wastewater System Im- provements | E100: 5000543 | F100: Simpson | H100: H
A101: Environmental Protection Agency | B101: STAG—Clean Water State Revolving Fund | C101: IL | D101: Bloomington-Normal Water Reclamation District for Pump Station and Force Main Project | E101: 1260000 | F101: LaHood | G101: Duckworth | H101: H/S
A102: Environmental Protection Agency | B102: STAG—Clean Water State Revolving Fund | C102: IL | D102: City of Aurora for Combined Storm and Sanitary Sewer Infrastructure Project | E102: 959752 | F102: Foster | H102: H
A103: Environmental Protection Agency | B103: STAG—Clean Water State Revolving Fund | C103: IL | D103: City of Bloomington for Sewer Separation | E103: 2000000 | F103: Sorensen | G103: Durbin | H103: H/S
A104: Environmental Protection Agency | B104: STAG—Clean Water State Revolving Fund | C104: IL | D104: City of Centralia for Water Treatment Plant Replacement | E104: 1000000 | F104: Bost | H104: H
A105: Environmental Protection Agency | B105: STAG—Clean Water State Revolving Fund | C105: IL | D105: City of Des Plaines for Sewer Lining Pro- gram | E105: 959757 | F105: Quigley | H105: H
A106: Environmental Protection Agency | B106: STAG—Clean Water State Revolving Fund | C106: IL | D106: City of Elmhurst for Waste Reclamation Facility | E106: 959752 | F106: Casten | H106: H
A107: Environmental Protection Agency | B107: STAG—Clean Water State Revolving Fund | C107: IL | D107: City of Lake Forest for Seminary Ravine Improvements | E107: 959752 | F107: Schneider | H107: H
A108: Environmental Protection Agency | B108: STAG—Clean Water State Revolving Fund | C108: IL | D108: City of Rolling Meadows for Park Street Storm Sewer Improvements | E108: 810000 | F108: Krishnamoorthi | H108: H
A109: Environmental Protection Agency | B109: STAG—Clean Water State Revolving Fund | C109: IL | D109: City of Staunton for Force Main Project | E109: 800000 | F109: Budzinski | H109: H
A110: Environmental Protection Agency | B110: STAG—Clean Water State Revolving Fund | C110: IL | D110: City of Wilmington for South Water and Sewer Main Extension Project | E110: 959752 | F110: Jackson (IL) | H110: H
A111: Environmental Protection Agency | B111: STAG—Clean Water State Revolving Fund | C111: IL | D111: Lake County for New Century Town Waste- water Treatment Plant Project | E111: 959752 | F111: Schneider | H111: H
A112: Environmental Protection Agency | B112: STAG—Clean Water State Revolving Fund | C112: IL | D112: Village of Bolingbrook for Water Reclama- tion Plant #3 Expansion Project | E112: 959752 | F112: Foster | H112: H
A113: Environmental Protection Agency | B113: STAG—Clean Water State Revolving Fund | C113: IL | D113: Village of Dieterich for Sanitary Sewer Re- lining | E113: 1000000 | F113: Bost | H113: H
A114: Environmental Protection Agency | B114: STAG—Clean Water State Revolving Fund | C114: IL | D114: Village of Hanover Park for Sanitary Sewer Lift Station Rehabilitation Project | E114: 800000 | F114: Krishnamoorthi | G114: Durbin | H114: H
A115: Environmental Protection Agency | B115: STAG—Clean Water State Revolving Fund | C115: IL | D115: Village of Pingree Grove for Waste Water Treatment Plant Upgrades Project | E115: 959752 | F115: Krishnamoorthi | H115: H
A116: Environmental Protection Agency | B116: STAG—Clean Water State Revolving Fund | C116: IL | D116: Village of Romeoville for Spangler Sanitary Lift Station Replacement | E116: 959757 | F116: Underwood | H116: H
A117: Environmental Protection Agency | B117: STAG—Clean Water State Revolving Fund | C117: IL | D117: Village of Rosemont for Graville Lift Sta- tion Enhancement Project | E117: 959752 | F117: Krishnamoorthi | H117: H
A118: Environmental Protection Agency | B118: STAG—Clean Water State Revolving Fund | C118: IL | D118: Village of Teutopolis for Watermain Re- placement | E118: 1000000 | F118: Bost | H118: H
A119: Environmental Protection Agency | B119: STAG—Clean Water State Revolving Fund | C119: IL | D119: Village of Wonder Lake for East Side Water System | E119: 959752 | F119: Schneider | H119: H
A120: Environmental Protection Agency | B120: STAG—Clean Water State Revolving Fund | C120: IN | D120: City of La Porte for Combined Sewer Sepa- ration Project | E120: 959752 | F120: Mrvan | H120: H
...

Sheet dwsrf_tracker
A1: community_served | B1: borrower | C1: pwsid | D1: project_id | E1: project_name | F1: project_type | G1: project_cost | H1: requested_amount | I1: funding_amount | J1: principal_forgiveness | K1: population | L1: project_description | M1: disadvantaged | N1: project_rank | O1: project_score | P1: expecting_funding | Q1: state | R1: state_fiscal_year
A2: Marion | B2: Fairview, Town of | C2: NA | D2: NA | E2: Phase I-Connection to Monumental PSD | F2: General | G2: 3179430 | H2: 2179430 | I2: 466000 | J2: 233000 | K2: 979 | L2: This preliminary application is to make improvements the Town of Fairview‚Äôs water distribution system and to connect to the Monumental PSD‚Äôs water system. The project will be split into two (2) phases. This application is for Phase I. Phase I will primarily consist of the installation of approximately 3,500 LF of 6"" water line, a PRV Station, a duplex booster station with telemetry and emergency generator, refurbish existing water storage tank, upgrade access roads to existing water storage tanks, upgrade telemetry to existing water storage tanks, demolish old tank at water treatment plant, decommission existing water treatment plant, a new office building, | M2: Yes | N2: 1 | O2: 100 | P2: Yes | Q2: West Virginia | R2: 2023
A3: Wyoming | B3: Pineville Municipal Waterworks | C3: NA | D3: NA | E3: Brenton/Baileysville Waterline Extensions | F3: General | G3: 9498871 | H3: 1912371 | I3: 2912371 | J3: 1000000 | K3: 2945 | L3: The proposed project consists of a new 8-inch line that will extend along WV Route 97 to Baileysville Elementary School from the end of the existing 8-inch line near Wyoming. Also there will be 6-inch lines extending from Route 97 along Lanes Branch Road and Doublecamp Branch Road for approximately 0.53 miles and 0.94 miles, respectively. This alternative will also feature one 150,000-gallon water storage tank | M3: Yes | N3: 2 | O3: 100 | P3: Yes | Q3: West Virginia | R3: 2023
A4: Hardy | B4: Wardensville, Town of | C4: NA | D4: NA | E4: Water System Improvements | F4: General | G4: 2421000 | H4: 3124477 | I4: 3421000 | J4: 1000000 | K4: 788 | L4: This project is to replace the fire hydrants and water meters in the distribution system; replace the Warden Acres water storage tank with a 330,000 gallon tank and the Anderson Ridge water storage tank with a 304,000 gallon tank: drill a new water well at the Town of Wardensville water treatment plant site; add a SCADA system; and upgrade/rehabilitate the existing Town of Wardensville‚Äôs water treatment plant with major work to consist of upgrade the electrical service, upgrade the chlorine room, upgrade mechanical piping, and add a generator. | M4: Yes | N4: 3 | O4: 90 | P4: Yes | Q4: West Virginia | R4: 2023
A5: Marion | B5: Fairview, Town of | C5: NA | D5: NA | E5: Phase II-Water line Replacements | F5: General | G5: 2175000 | H5: 1175000 | I5: 344000 | J5: 172000 | K5: 979 | L5: This project will replace 11,000 ft of old water mains, install 14 new valves and 5 fire hydrants in order to reduce significant water loss. | M5: Yes | N5: 4 | O5: 90 | P5: Yes | Q5: West Virginia | R5: 2023
A6: Harrison | B6: Salem, City of | C6: NA | D6: NA | E6: Phase IV Water System Improvements | F6: General | G6: 3500000 | H6: 2400000 | I6: No Information | J6: No Information | K6: 1617 | L6: The City of Salem is proposing to replace approximately 1.5 miles (8,000 LF) of problematic 8-inch water main, along with short sections of 6-inch connection lines, utility service lines (including lead and galvanized) and 128 water meters. Two short sections of 2-inch water line will also be replaced and a leak detection will be performed on the rest of the distribution system. | M6: Yes | N6: 5 | O6: 90 | P6: No | Q6: West Virginia | R6: 2023
A7: McDowell | B7: McDowell County PSD | C7: NA | D7: NA | E7: Elkhorn Ph III | F7: General | G7: 7513000 | H7: 856500 | I7: 1713000 | J7: 856500 | K7: 693 | L7: The proposed project will construct a new water treatment plant to serve 220 customers and will allow 3 old treatment plants (Greenbrier, Ashland, and Crumpler) to be retired in the area. Also included in the project will be a 50 GPM booster station, (2) 100,000-gallon water storage tanks, approximately 60,645 linear feet of 8- inch and smaller waterline, 24 fire hydrants, and all other necessary valves and appurtenances. | M7: Yes | N7: 6 | O7: 80 | P7: Yes | Q7: West Virginia | R7: 2023
A8: Pendleton | B8: Town of Franklin | C8: NA | D8: NA | E8: Plant Upgrade/Line Replacement | F8: General | G8: 3472318 | H8: 1300000 | I8: 2772318 | J8: 500000 | K8: 1702 | L8: The proposed project consists of: 8‚Äù directional drill river crossing, upgrades at the Hanover Storage Tank, replacement of the altitude valve, and upgrades to the Morton Storage Tank. At the water treatment plant work includes; upgrade secondary water source, replace backwash pump, upgrade backwash tank, upgrade plant instrumentation, upgrade plant building, and upgrade sediment basin, Installation of two 40,000 gallon clear well tanks, new automation, VFD‚Äôs on pump motors, new automatic transfer switch, and replace the plant emergency generator. | M8: Yes | N8: 7 | O8: 80 | P8: Yes | Q8: West Virginia | R8: 2023
A9: Barbour | B9: Chestnut Ridge PSD | C9: NA | D9: NA | E9: Water System Improvements | F9: General | G9: 5300000 | H9: 500000 | I9: 1902500 | J9: No Information | K9: 2643 | L9: This project will make improvements to the PSD's water distribution system, including water line and valve replacement, upgrading booster stations, replacing water meters and upgrades to the SCADA and telemetry systems. | M9: Yes | N9: 8 | O9: 80 | P9: Yes | Q9: West Virginia | R9: 2023
A10: Mercer | B10: Mercer County PSD | C10: NA | D10: NA | E10: Water System Improvements | F10: General | G10: 2698000 | H10: 2698000 | I10: No Information | J10: No Information | K10: No Information | L10: This project will extend the water system to the McComas area and replace the existing failing McComas water system. | M10: No Information | N10: 9 | O10: 75 | P10: No | Q10: West Virginia | R10: 2023
A11: Morgan | B11: Paw Paw, Town of | C11: NA | D11: NA | E11: Water System Improvements | F11: General | G11: 4395600 | H11: 3395600 | I11: No Information | J11: No Information | K11: 488 | L11: This Preliminary Application is to upgrade the Town of Paw Paw water treatment plant and distribution system. The distribution portion of the project will consist of the installation of approximately 2 miles (10,780 LF) of 2"" to 8‚Äù water line; and rehabilitate the existing water storage tanks. | M11: Yes | N11: 10 | O11: 70 | P11: No | Q11: West Virginia | R11: 2023
A12: Nicholas | B12: Richwood, City of | C12: NA | D12: NA | E12: Surface Water Intake Impound Structure Project | F12: General | G12: 2000000 | H12: 1000000 | I12: 900000 | J12: 200000 | K12: 1095 | L12: The proposed project will replace the raw water intake impoundment that helps to regulate the water level around the water treatment plant‚Äôs raw water intake. Included in this project will be building a new surface water intake impound structure, demolition and removal of the existing impound infrastructure, installation of a catwalk with manual gate, construction of a new intake screening structure, approximately 200 LF of 12‚Äù mains, 300 LF of 2‚Äù air line and site electric with equipment for an air compressor building, and various reclamation of disturbed areas. | M12: Yes | N12: 11 | O12: 70 | P12: Yes | Q12: West Virginia | R12: 2023
A13: Ritchie | B13: Pennsboro, City of | C13: NA | D13: NA | E13: Water System Improvements | F13: General | G13: 2112000 | H13: 500000 | I13: 1000000 | J13: 500000 | K13: 1291 | L13: The proposed project plans to replace the existing 434,000 gallon Industrial Park Tank with a new like-sized tank and to rehabilitate the Park Drive and Broadwater Water Storage Tanks. Also included will be the replacement of almost 1.14 miles of mostly 8-inch watermains with a small portion being 2-inch and 6-inch. All necessary valves and appurtenances will be included as well as the demolition and site preparation for the new tank. | M13: Yes | N13: 12 | O13: 70 | P13: Yes | Q13: West Virginia | R13: 2023
A14: Greenbrier | B14: Alderson, Town of | C14: NA | D14: NA | E14: Water System Rehab & Expansion | F14: General | G14: 9013000 | H14: 5398000 | I14: 7360258 | J14: 2699000 | K14: 2458 | L14: This preliminary application is for the Town of Alderson to extend water service to the Riverside Rest area and to repair/replace various parts of the water distribution system and water treatment facilities. | M14: Yes | N14: 13 | O14: 70 | P14: Yes | Q14: West Virginia | R14: 2023
A15: Wyoming | B15: Town of Oceana | C15: NA | D15: NA | E15: Water System Upgrade Phase II | F15: General | G15: 5000000 | H15: 3000000 | I15: 1905076 | J15: 952538 | K15: 3797 | L15: Phase 2 of a water system upgrade project for the Town of Oceana and the surrounding area. Project includes replacing Lynco water storage tank, water plant upgrades, telemetry upgrades, replacing water meters, booster station upgrades, and upgrading existing water lines along Rt 10, Rt 85, Popular St. and Chestnut St. | M15: Yes | N15: 14 | O15: 70 | P15: Yes | Q15: West Virginia | R15: 2023
A16: McDowell | B16: Gary, City of | C16: NA | D16: NA | E16: Water System Improvements | F16: General | G16: 3587000 | H16: 500000 | I16: No Information | J16: No Information | K16: 1633 | L16: The project includes the engineering services necessary to conduct a feasibility study that will review alternate water sources for the city's water distribution system. Including alternative raw water sources, emergency interconnect to the City of Welch, emergency interconnect to the McDowell County PSD and consolidation with a nearby water utility. | M16: Yes | N16: 15 | O16: 65 | P16: No | Q16: West Virginia | R16: 2023
A17: Lincoln | B17: Lincoln PSD | C17: NA | D17: NA | E17: Alum Creek Water Storage Tank Replacement | F17: General | G17: 1000000 | H17: 250000 | I17: 500000 | J17: 250000 | K17: 2473 | L17: This project will replace the Lincoln PSD‚Äôs Alum Creek Water Storage Tank with a new 300,000 gallon tank. | M17: Yes | N17: 16 | O17: 65 | P17: Yes | Q17: West Virginia | R17: 2023
A18: Ritchie | B18: Cairo, Town of | C18: NA | D18: NA | E18: Water System Improvements | F18: General | G18: 4000000 | H18: 1000000 | I18: 1000000 | J18: 500000 | K18: 406 | L18: This project will make improvements to the Town of Cairo water distribution system. The project will consist of the 190 new water meters, replacement of 20 valves, replace the existing PRV station, clean and refurbish the existing 214,000 gallon storage tank, replace a river crossing; stabilize a river bank, replace 12 fire hydrants, install 12 fire hydrants, replace approximately 2.5 miles (13,400 LF) of 6"" and 2"" water line, and replace approximately 1.1 miles (6,000 LF) of 3/4"" water line. | M18: Yes | N18: 17 | O18: 65 | P18: Yes | Q18: West Virginia | R18: 2023
A19: Marion | B19: Town of Worthington | C19: NA | D19: NA | E19: Worthington Line Upgrades/Replacement | F19: General | G19: 3366390 | H19: 2866390 | I19: 2799200 | J19: 500000 | K19: 1099 | L19: The project will make upgrades to the Town‚Äôs distribution system and will include an interconnection between Four States and Monongah. The project also includes a water line extension to the Harter Hill area that will serve five (5) new customers. The project will consist of the installation of approximately 18,900 LF of 6"" and 18,000 LF of 2"" water line; 10,000 LF of ¬æ"" service line replacement; 28 valves; two (2) PRV Stations; 12 fire hydrants; two (2) solenoid master meters; 13 leak detection meters; 465 radio-read meters; all necessary piping, valves and appurtenances. | M19: Yes | N19: 18 | O19: 65 | P19: Yes | Q19: West Virginia | R19: 2023
A20: Marion | B20: Grant Town, Town of | C20: NA | D20: NA | E20: Water System Improvements | F20: General | G20: 3825000 | H20: 2825000 | I20: No Information | J20: No Information | K20: 1240 | L20: This Preliminary Application is to replace water line, booster stations and water storage tank in the Town of Grant Town. The project will consist of the installation of approximately 2.9 miles (15,125 LF) of 8""through 2"" waterline; replace two (2) booster stations; and replace the existing 100,000-gallon tank with a new 200,000- gallon tank; and necessary valves and appurtenances. | M20: Yes | N20: 19 | O20: 65 | P20: No | Q20: West Virginia | R20: 2023
A21: Preston | B21: Terra Alta Municipal Water Dept. | C21: NA | D21: NA | E21: Water System Extensions and Improvements | F21: General | G21: 6250000 | H21: 4800000 | I21: No Information | J21: No Information | K21: 1856 | L21: This preliminary application is to extend water service to 25 new customers and to upgrade/replace the water system in the Town of Terra Alta. The water distribution section of the project will consist of the installation of approximately 1.5 miles (8,100 LF) of 2"" and 6.2 miles (32,800 LF) of 8"" water line; replace the 200,000 gallon Goodwill water storage tank; replace the Corinth water storage tank altitude valve; replace all meters with radio read meters; purchase a compact excavator, equipment trailer and a service dump truck; and all necessary valves, controls and appurtenances. The water treatment portion of the project will consist of a new high | M21: Yes | N21: 20 | O21: 65 | P21: No | Q21: West Virginia | R21: 2023
A22: Mineral | B22: New Creek Water Association | C22: NA | D22: NA | E22: Water System Improvements | F22: General | G22: 5673000 | H22: 5673000 | I22: No Information | J22: No Information | K22: 3043 | L22: This project proposes to make several upgrades around the water system including waterline replacements, waterline extensions, tank replacement, Booster Pump Station Upgrades and various other system upgrades. | M22: Yes | N22: 21 | O22: 65 | P22: No | Q22: West Virginia | R22: 2023
A23: Marion | B23: Rivesville, Town of | C23: NA | D23: NA | E23: Fairmont to Rivesville Water Supply Line Project | F23: General | G23: 3206307 | H23: 500000 | I23: No Information | J23: No Information | K23: 1443 | L23: The proposed project includes replacing the deteriorated 8‚Äù main supply line with a 12‚Äù line that will connect to the City of Fairmont‚Äôs 16‚Äù main. This project will consist constructing 10,500 feet (2 mi) of 12‚Äù water line and 300 feet of 8‚Äù water line within a stream crossing, 350 feet of steel casing and 6 gate valves. The City of Fairmont provides water to the Town of Rivesville. The intent is to ultimately transfer ownership of a portion of the line to the City of Fairmont. | M23: Yes | N23: 22 | O23: 60 | P23: No | Q23: West Virginia | R23: 2023
A24: Fayette | B24: Pax, Town of | C24: NA | D24: NA | E24: Water System Upgrades | F24: General | G24: 1680000 | H24: 1680000 | I24: No Information | J24: No Information | K24: 762 | L24: This project proposes replacing sections of water main between the Beckley Water Company connection point and the Pax water tank. The proposed project will consist of approximately 1.9 miles (10,000 LF) of 6‚Äù PVC, 400 LF of 6‚Äù DIP, 600 LF of 8‚Äù HDPE, 400 LF of 2‚Äù PVC, five stream crossings, five Department of Highway road crossings, and related appurtenances. This will renew the useful life of this critical section of waterline and will continue to distribute treated water for the Town of Pax customers. | M24: Yes | N24: 23 | O24: 60 | P24: No | Q24: West Virginia | R24: 2023
A25: Mason | B25: Mason County PSD | C25: NA | D25: NA | E25: J2Y35 Water System Improvements | F25: General | G25: 1400000 | H25: 500000 | I25: No Information | J25: No Information | K25: 3323 | L25: This project includes Miscellaneous improvements to existing J2Y35 water association water system in order for the Mason County PSD to adequately operate it through feeding it from its system, including 10,000 LF 8 inch transmission line to connect PSD system to J2Y35 tank; 125 gpm booster station near tie in; replace J2Y35 89,300 gallon tank; PRV valve vault for existing customers fed through 22nd Street master meter | M25: Yes | N25: 24 | O25: 60 | P25: No | Q25: West Virginia | R25: 2023
A26: Upshur | B26: Hodgesville PSD | C26: NA | D26: NA | E26: Water System Improvements & Extension | F26: General | G26: 7000000 | H26: 2320000 | I26: No Information | J26: No Information | K26: 2887 | L26: This project will replace approximately 175 service lines in the existing system. It will also include an extension on the Upper Peck's Run Road to serve an additional five customers. The project includes the installation of two 100,000 gallon water tanks as well as a booster pump station. The project also includes the installation of approximately 1200 radio read meters. | M26: Yes | N26: 25 | O26: 60 | P26: No | Q26: West Virginia | R26: 2023
A27: Roane | B27: Walton PSD | C27: NA | D27: NA | E27: Camp Shepard-Quarry Road Water Line Extensions | F27: General | G27: 3459710 | H27: 959710 | I27: No Information | J27: No Information | K27: 1986 | L27: This project will upgrade the line size to the Camp Shepard 4-H camp to provide fire protection and then extend the line out to serve approximately 26 new customers along Wolf Run and Quarry Road. Included will be approximately 3.7 miles of water line , (2) fire hydrants, a booster station, (1) 50,000 gallon water storage tank, and all necessary valves and appurtenances. They also plan to repaint the 100,000 gallon Walton water storage tank and refurbish the Gandeeville, Ambler Ridge, and Long Ridge water storage tanks. | M27: Yes | N27: 26 | O27: 55 | P27: No | Q27: West Virginia | R27: 2023
A28: Summers | B28: Jumping Branch Nimitz PSD | C28: NA | D28: NA | E28: Broomstraw Rd./Mark Meador Rd. Extension | F28: General | G28: 4811800 | H28: 400000 | I28: No Information | J28: No Information | K28: 1414 | L28: This project will provide water service to the Broomstraw Rd. and Mark Meador Rd. areas of western Summers County. Residents experience low water quality and poor quality water issues in existing private wells. In addition, many residents haul water, use cisterns, and some report fecal contaminants in wells. | M28: Yes | N28: 27 | O28: 53 | P28: No | Q28: West Virginia | R28: 2023
A29: Summers | B29: Jumping Branch Nimitz PSD | C29: NA | D29: NA | E29: Madams Creek Waterline Ext. | F29: General | G29: 4418500 | H29: No Information | I29: No Information | J29: No Information | K29: 1414 | L29: To provide water service to the Madams Creek Rd. area of western Summers Co. Residents experience low water quality and poor quality water issues in existing private wells. In addition, man residents haul water, use cisterns, and some report fecal contaminants in wells. | M29: Yes | N29: 28 | O29: 53 | P29: No | Q29: West Virginia | R29: 2023
A30: Webster | B30: Cowen PSD | C30: NA | D30: NA | E30: Rt. 82 Water Line Extension Project | F30: General | G30: 4500000 | H30: 3000000 | I30: No Information | J30: No Information | K30: 2796 | L30: This project consists of extending public water service and providing fire service to approximately 55 proposed customers along Rt. 82 in Webster County. | M30: Yes | N30: 29 | O30: 53 | P30: No | Q30: West Virginia | R30: 2023
A31: Harrison | B31: Anmoore, Town of | C31: NA | D31: NA | E31: Water System Improvements | F31: General | G31: 3300000 | H31: 2300000 | I31: No Information | J31: No Information | K31: 951 | L31: This Preliminary Application is to replace existing water line in the Town of Anmoore with approximately 5.2 miles (27,380 LF) of 8"" thru 2‚Äù water line, approximately 1.5 miles of service line (8,080 LF) and approximately 456 new radio read meters. | M31: Yes | N31: 30 | O31: 50 | P31: No | Q31: West Virginia | R31: 2023
A32: Pocahontas | B32: Marlinton, Town of | C32: NA | D32: NA | E32: Phase II Water System Improvements | F32: General | G32: 4500000 | H32: 3500000 | I32: No Information | J32: No Information | K32: 1362 | L32: This project is Phase 2 for Marlinton‚Äôs water distribution system improvements. The project will replace approximately 1.9 miles of existing 4-inch water mains with 6- inch water line and replace approximately 1.9 miles of existing 1.25-inch water line with 2-inch water line. Also included will be to installation of 41 valves, 20 fire hydrants, 10 leak detector meters, replace 300 meters/wells/setters, and all other necessary valves and appurtenances. | M32: Yes | N32: 31 | O32: 50 | P32: No | Q32: West Virginia | R32: 2023
A33: Webster | B33: Cowen PSD | C33: NA | D33: NA | E33: Ph III Water System Rehabilitation Project | F33: General | G33: 11580000 | H33: 2580000 | I33: No Information | J33: No Information | K33: 3372 | L33: Project will remove and replace approx. 17,050 lf of water lines ranging in size from 2"" to 10"" and rehabilitate the existing WTP and upgrade the capacity from 600 GPM to 1,200 GPM | M33: Yes | N33: 32 | O33: 50 | P33: No | Q33: West Virginia | R33: 2023
A34: Mingo | B34: Williamson, City of | C34: NA | D34: NA | E34: Water System Upgrade Project | F34: General | G34: 12578000 | H34: 12578000 | I34: No Information | J34: No Information | K34: 4183 | L34: This project will upgrade the water treatment, storage and distribution system. Upgrades will consist of the installation of (3) 2,500 GPM treatment high service pumps, approx. 2.86 miles of 24-inch and smaller diameter mains, a 500 GPM booster pump station, four new water storage tanks, rehab of existing tank, numerous pressure reducing stations, back up generators for TP and booster pump stations, telemetry, hydrants, valves, meters | M34: Yes | N34: 33 | O34: 50 | P34: No | Q34: West Virginia | R34: 2023
A35: McDowell | B35: McDowell County PSD | C35: NA | D35: NA | E35: Bradshaw | F35: General | G35: 2000000 | H35: 100000 | I35: No Information | J35: No Information | K35: 1854 | L35: This project proposes that the Bradshaw water system will be connected to the McDowell County PSD Bartley water distribution system that runs through town, and the water will be supplied by the MCPSD Bartley WTP. In addition it will involve the decommissioning of the Bradshaw Water Treatment Plant and the Bradshaw water tank. This project will result in the consolidation of Bradshaw Water Works and McDowell Co. PSD ‚Äì Bartley. | M35: Yes | N35: 34 | O35: 50 | P35: No | Q35: West Virginia | R35: 2023
A36: Fayette | B36: New Haven PSD | C36: NA | D36: NA | E36: Contract 18 - Sunday Rd./Confluence/Elliott Cutoff area. | F36: General | G36: 2933635 | H36: 2493325 | I36: 753884 | J36: 376942 | K36: 4409 | L36: Water line extension to Sunday Rd./Confluence/Elliot Cufoff area, including possible Stringtown connector & Clifty connector. Approximately 67 new customers. | M36: Yes | N36: 35 | O36: 48 | P36: Yes | Q36: West Virginia | R36: 2023
A37: Fayette | B37: New Haven PSD | C37: NA | D37: NA | E37: Contract 19 - Ramsey Extension | F37: General | G37: 4841686 | H37: 3927250 | I37: 1089841 | J37: 337600 | K37: 4438 | L37: Water line extension to Cane Branch, Ramsey, Hawver Rd., South Miller Ridge, Arrowwood Rd., Dotson Ridge & Lower Dotson Ridge, Whispering Pines. Approximately 73 new customers. | M37: Yes | N37: 36 | O37: 48 | P37: Yes | Q37: West Virginia | R37: 2023
A38: Greenbrier | B38: Greenbrier County PSD #2 | C38: NA | D38: NA | E38: Ph II- Sam Black Water Line Extension | F38: General | G38: 17000000 | H38: 9000000 | I38: No Information | J38: No Information | K38: 2326 | L38: This project extends water service to approximately 475 new customers from Charmco to Rainelle and from Sam Black Church to Asbury in Greenbrier County. The project includes approximately 17 miles of 2-inch to 8-inch distribution line, two (2) booster stations, one (1) 100,000-gallon water storage tank, one (1) 300,000 gallon water storage tank, 50 gate valves, 40 fire hydrants, 30 flushing hydrants and other appurtenances. | M38: Yes | N38: 37 | O38: 45 | P38: No | Q38: West Virginia | R38: 2023
A39: Mercer | B39: Lashmeet PSD | C39: NA | D39: NA | E39: Mary Branch Water Extension | F39: General | G39: 2146050 | H39: 971453 | I39: 1279921 | J39: 214753 | K39: 3794 | L39: Extension of public water to the Mary Branch area of Mercer County, West Virginia. 4 miles. Approximately 42 new customers. | M39: Yes | N39: 38 | O39: 40 | P39: Yes | Q39: West Virginia | R39: 2023
A40: Brooke | B40: Hammond PSD | C40: NA | D40: NA | E40: Water System Improvements | F40: General | G40: 6174000 | H40: 5674000 | I40: No Information | J40: No Information | K40: 2196 | L40: This project includes system improvements to the distribution systems and the water treatment plant. This includes water main replacement, replacing exiting meters with new AMR meters, replacing shut off valves, pump station improvements and upgrades to existing water storage tanks. Water treatment plant improvements include replacing the sedimentation basin, filter media replacement, automatic valve installation, installation of a permanent generator and pump replacement. | M40: Yes | N40: 39 | O40: 40 | P40: No | Q40: West Virginia | R40: 2023
A41: Fayette | B41: Kanawha Falls PSD | C41: NA | D41: NA | E41: Water System Improvements | F41: General | G41: 9860500 | H41: 9860500 | I41: No Information | J41: No Information | K41: 2410 | L41: This project will upgrade the existing water treatment plant from approximately 933 gpm to 1,300 gpm. | M41: Yes | N41: 40 | O41: 40 | P41: No | Q41: West Virginia | R41: 2023
A42: Nicholas | B42: Craigsville PSD | C42: NA | D42: NA | E42: Water Treatment Plant and Distribution System Upgrades | F42: General | G42: 11100000 | H42: 3174000 | I42: 2407952 | J42: 400000 | K42: 1813 | L42: This project will upgrade the existing water treatment plant to 900 gpm and installing a dedicated waterline from the water treatment plant to existing elevated water storage tanks. The project will consist of a new raw water intake screen and hydroburst system, raw water pump station, flocculator, sedimentation basin, filter equipment, backwash solids pump station, chemical feed system, painting four (4) existing water tanks, approximately 4 miles of 10"" water line, and all necessary appurtenances. | M42: Yes | N42: 41 | O42: 35 | P42: Yes | Q42: West Virginia | R42: 2023
A43: Harrison | B43: Town of Nutter Fort | C43: NA | D43: NA | E43: Water System Improvements | F43: General | G43: 4300000 | H43: 2000000 | I43: No Information | J43: No Information | K43: 1832 | L43: This project will replace water line and add a new water storage tank in the Town of Nutter Fort. The project will consist of the installation of approximately 1.3 miles (7,110 LF) of 6"" and 1.5 miles (7,850 LF) of 12"" waterline and one (1) 270,000- gallon water storage tank with telemetry and all necessary valves and appurtenances. | M43: Yes | N43: 42 | O43: 33 | P43: No | Q43: West Virginia | R43: 2023
A44: Doddridge | B44: West Union, Town of | C44: NA | D44: NA | E44: Water System Improvements | F44: General | G44: 22995000 | H44: 20995000 | I44: No Information | J44: No Information | K44: 1895 | L44: The proposed project will include improvements to the distribution system and a construction of a new 500 GPM water treatment plant. Improvements include 11,000 ft of new water line, two new water storage tanks, new telemetry and replacement of 16,200 ft of water line. | M44: Yes | N44: 43 | O44: 30 | P44: No | Q44: West Virginia | R44: 2023
A45: Hancock | B45: City of Weirton | C45: NA | D45: NA | E45: Water Treatment Plant Refurbish & Expand | F45: General | G45: 22470000 | H45: 2000000 | I45: No Information | J45: No Information | K45: 24000 | L45: This project will upgrade and increase the Weirton Water Board‚Äôs 4.0 MGD Water Treatment Plant to an 8.0 MGD plant. Major new construction will consist of a pre- sedimentation basin with sludge removal equipment, a flocculation tank with plate settlers, a sludge thickener, a backwash filter tank, an emergency generator and the expansion of the existing filter building and clear well. The existing Raney Well will also be reconstructed. | M45: Yes | N45: 44 | O45: 25 | P45: No | Q45: West Virginia | R45: 2023
A46: Fayette | B46: Bellwood Community Facilities | C46: NA | D46: NA | E46: Main Line Replacement | F46: General | G46: 5000 | H46: 5000 | I46: No Information | J46: No Information | K46: 113 | L46: Project will replace 40 yr. old 2"" galvanized supply line from pump house to tank reservoir, approx. 600 ft. | M46: No Information | N46: 45 | P46: No | Q46: West Virginia | R46: 2023
A47: Preston | B47: Arthurdale Water Association | C47: NA | D47: NA | E47: Water System Upgrades | F47: General | G47: 200000 | H47: 200000 | I47: No Information | J47: No Information | K47: 285 | L47: Project consists of water treatment plant and distribution system upgrades. | M47: No Information | N47: 46 | P47: No | Q47: West Virginia | R47: 2023
A48: Ohio | B48: Valley Grove, Village of | C48: NA | D48: NA | E48: Water System Improvements | F48: General | G48: 7500000 | H48: 6500000 | I48: No Information | J48: No Information | K48: 686 | L48: This project includes replacement of approx. 35,000 lf of water lines, construction of 2 new 100,000 gallon storage tanks, 250 new water meters, and water tank access road improvements. | M48: Yes | N48: 47 | P48: No | Q48: West Virginia | R48: 2023
A49: Tucker | B49: Thomas, City of | C49: NA | D49: NA | E49: Water System Improvements | F49: General | G49: 15300000 | H49: 14300000 | I49: No Information | J49: No Information | K49: 753 | L49: Project includes replacement of 35,000 lf of existing water lines, rehabilitation of 3 water storage tanks, replacement of 1 booster pump station, a new 350 gpm water treatment plant, replacement of 360 water meters, and 3,000 lf of new 8"" water line. | M49: Yes | N49: 48 | P49: No | Q49: West Virginia | R49: 2023
A50: Harrison | B50: Summit Park PSD | C50: NA | D50: NA | E50: Water System Improvements | F50: General | G50: 6000000 | H50: 6000000 | I50: No Information | J50: No Information | K50: 835 | L50: Project will replace all existing components of an aging water system with new line and lead free components. | M50: No Information | N50: 49 | P50: No | Q50: West Virginia | R50: 2023
A51: Preston | B51: Rowlesburg, Town of | C51: NA | D51: NA | E51: Water System Improvements | F51: General | G51: 2000000 | H51: 1500000 | I51: No Information | J51: No Information | K51: 892 | L51: The project proposes to repair electrical issues and perform upgrades at the water treatment plant. The project also proposes to purchase and install new water meters within the system, purchase leak detection equipment, and upgrade aging water lines. | M51: Yes | N51: 50 | P51: No | Q51: West Virginia | R51: 2023
A52: Barbour | B52: Junior, Town of | C52: NA | D52: NA | E52: Water Tank Replacement Project | F52: General | G52: No Information | H52: No Information | I52: No Information | J52: No Information | K52: 987 | L52: This project will replace a water storage tank that was constructed in 1970 and is in poor condition. | M52: Yes | N52: 51 | P52: No | Q52: West Virginia | R52: 2023
A53: Mineral | B53: Fountain PSD | C53: NA | D53: NA | E53: Parrill Hollow Water System ProjectTBD | F53: General | G53: 2202800 | H53: 822630 | I53: No Information | J53: No Information | K53: 1001 | L53: No Information | M53: Yes | N53: 52 | P53: No | Q53: West Virginia | R53: 2023
A54: Calhoun | B54: Mt. Zion PSD | C54: NA | D54: NA | E54: Water System Improvements | F54: General | G54: 2500000 | H54: 1500000 | I54: No Information | J54: No Information | K54: 1009 | L54: Project includes water distribution and storage system improvements. | M54: Yes | N54: 53 | P54: No | Q54: West Virginia | R54: 2023
A55: Marion | B55: Downs PSD | C55: NA | D55: NA | E55: Waterline Extensions & System Upgrades | F55: General | G55: 2400000 | H55: 2400000 | I55: No Information | J55: No Information | K55: 1024 | L55: Project includes water line extensions along East Run and Plum Run Road, construction of a water storage tank and an interconnection with Monumental PSD to allow a secondary source to both utilities. | M55: Yes | N55: 54 | P55: No | Q55: West Virginia | R55: 2023
A56: Pleasants | B56: Belmont, City of | C56: NA | D56: NA | E56: Water System Improvements | F56: General | G56: 3500000 | H56: 1000000 | I56: No Information | J56: No Information | K56: 1048 | L56: Project consists of distribution and storage system upgrades. | M56: No | N56: 55 | P56: No | Q56: West Virginia | R56: 2023
A57: Nicholas | B57: Richwood, City of | C57: NA | D57: NA | E57: Water Tank Renovation and Meter Replacement | F57: General | G57: 5000000 | H57: 5000000 | I57: No Information | J57: No Information | K57: 1095 | L57: This project includes the engineering services necessary to renovate 4 finished water storage tanks, demolish 1 water storage tank, add a booster station, replace existing obsolete water meters, and construct a presedimentation basin. | M57: Yes | N57: 56 | P57: No | Q57: West Virginia | R57: 2023
A58: Marion | B58: Ice's Run Rt 250 PSD | C58: NA | D58: NA | E58: Water System Improvements PH II | F58: General | G58: 2400000 | H58: 2400000 | I58: No Information | J58: No Information | K58: 1130 | L58: This project includes replacement of 9,200 lf of existing water line, improvements to Goose Run booster pump station, new booster station, new water meters, water tank access road improvements, new control valve station and telemetry system upgrades. | M58: No Information | N58: 57 | P58: No | Q58: West Virginia | R58: 2023
A59: Braxton | B59: Burnsville Public Utility Board | C59: NA | D59: NA | E59: Route 4 Water Line Extension | F59: General | G59: 6700000 | H59: 6700000 | I59: No Information | J59: No Information | K59: 1140 | L59: This project would extend public water service to approx. 100 customers from Curry Ridge along Route 4 to the Lewis County line. | M59: Yes | N59: 58 | P59: No | Q59: West Virginia | R59: 2023
A60: Braxton | B60: Burnsville Public Utility Board | C60: NA | D60: NA | E60: Water System Rehab Project | F60: General | G60: 6000000 | H60: 1200000 | I60: No Information | J60: No Information | K60: 1140 | L60: Proposed water line extension and relocation project to provide water service to customers along Curry Ridge Rd. and remove the existing water line from the Corp of Engineers Burnsville Lake. | M60: Yes | N60: 59 | P60: No | Q60: West Virginia | R60: 2023
A61: Ritchie | B61: Pennsboro, City of | C61: NA | D61: NA | E61: Phase II Water Line Extension | F61: General | G61: 5000000 | H61: 4000000 | I61: No Information | J61: No Information | K61: 1291 | L61: This project will extend public water to approx. 33 customers along Route 74. The project includes water lines, water meters, fire hydrants and all necessary appurtenances. | M61: Yes | N61: 60 | P61: No | Q61: West Virginia | R61: 2023
A62: Hancock | B62: New Cumberland, City of | C62: NA | D62: NA | E62: New Well | F62: General | G62: 150000 | H62: 150000 | I62: No Information | J62: No Information | K62: 1326 | L62: This project includes development of a new well, repairing an existing well and replacement of approx. 30 valves. | M62: Yes | N62: 61 | P62: No | Q62: West Virginia | R62: 2023
A63: Summers | B63: Big Bend PSD | C63: NA | D63: NA | E63: Water System Improvements | F63: General | G63: 2540000 | H63: 2540000 | I63: No Information | J63: No Information | K63: 1338 | L63: Project consists of water line replacements under the Greenbrier River, installation of a generator and transfer switch at the Hillsdale booster station and WTP improvements. | M63: No Information | N63: 62 | P63: No | Q63: West Virginia | R63: 2023
A64: Tucker | B64: Parsons, City of | C64: NA | D64: NA | E64: Water System Improvements | F64: General | G64: 4500000 | H64: 4500000 | I64: No Information | J64: No Information | K64: 1461 | L64: The project includes upgrades to existing potable water storage, replacement of remaining original sections of the water system, replacement of hydrants and valves, and upgrades to leak detection monitoring systems. | M64: Yes | N64: 63 | P64: No | Q64: West Virginia | R64: 2023
... A72: Grant | B72: Mountain Top PSD | C72: NA | D72: NA | E72: Water Meter System Upgrades | F72: General | G72: 600000 | H72: 600000 | I72: No Information | J72: No Information | K72: 2072 | L72: This project will purchase and install a complete radio read meter system throughout the district to increase system efficiency and accountability. | M72: No Information | N72: 71 | P72: No | Q72: West Virginia | R72: 2023
A73: Jefferson | B73: Harpers Ferry Water Works | C73: NA | D73: NA | E73: Water System Improvements | F73: General | G73: 9635200 | H73: No Information | I73: No Information | J73: No Information | K73: 2122 | L73: This project will upgrade the water distribution system in the Harpers Ferry Water Works service area using PSC approved plans not implemented in 2021 due to cost overruns. | M73: No | N73: 72 | P73: No | Q73: West Virginia | R73: 2023
A74: Harrison | B74: Greater Harrison Co PSD | C74: NA | D74: NA | E74: Water System Improvements PH II | F74: General | G74: 7185000 | H74: 4000000 | I74: No Information | J74: No Information | K74: 2159 | L74: This project will upgrade multiple sections of the entire water systems including replacement in McWorter, upsizing lines in Quiet Dell and Brushy Fork. The project also will extend public water service to residents on Hastings Run Rd. and Duck Creek Rd. Replacement of two existing water storage tanks is also included in the project scope. | M74: No Information | N74: 73 | P74: No | Q74: West Virginia | R74: 2023
A75: Ritchie | B75: Harrisville, Town of | C75: NA | D75: NA | E75: Mellin Ridge Water Line Extension | F75: General | G75: 3200000 | H75: 2200000 | I75: No Information | J75: No Information | K75: 2246 | L75: This project will extend public water service west from the Washburn Pump Station along Gillespie Run Road and Mellin Ridge Road. The proposed extension will provide potable water service to approximately 60 new customers. The extension will consist of the installation of approximately 52,300 linear feet (LF) of new water pipe ranging in size from six (6) inches to two (2) inches in diameter. The existing Washburn pump station will also be upgraded with new pumps. a SCADA system. and other equipment to support the increased water distribution demand due to this project. | M75: No Information | N75: 74 | P75: No | Q75: West Virginia | R75: 2023
A76: Taylor | B76: Mountain View Water Assoc. | C76: NA | D76: NA | E76: Water System Improvements | F76: General | G76: 6700000 | H76: 6700000 | I76: No Information | J76: No Information | K76: 2263 | L76: Project includes 16,000lf of water line extension, 55,100lf of failing water line replacement, a new booster pump station, and repair of an existing PRV. | M76: No Information | N76: 75 | P76: No | Q76: West Virginia | R76: 2023
A77: Barbour | B77: Century Volga PSD | C77: NA | D77: NA | E77: Water System Improvements | F77: General | G77: 2000000 | H77: 1700000 | I77: No Information | J77: No Information | K77: 2492 | L77: Project includes replacing the liquid level indicator at 2 storage tanks, construction of one new 1,000 gallon storage tank, repair or replacment of two PRV stations and replacing approx. 1000 water meters. | M77: Yes | N77: 76 | P77: No | Q77: West Virginia | R77: 2023
A78: Jackson | B78: Northern Jackson County PSD | C78: NA | D78: NA | E78: Sarvis Fork Extension | F78: General | G78: 1575000 | H78: 1575000 | I78: No Information | J78: No Information | K78: 2506 | L78: This project will provide public water service and fire protection to approx. 15 homes in the Sarvis Fork area. Project includes approx. 18,880 lf of 6 through 2 inch water line. | M78: Yes | N78: 77 | P78: No | Q78: West Virginia | R78: 2023
A79: Harrison | B79: Sun Valley PSD | C79: NA | D79: NA | E79: Cherry Camp Extension to Rt 23 | F79: General | G79: 8500000 | H79: 4000000 | I79: No Information | J79: No Information | K79: 2657 | L79: This project proposes to extend public water service along State Routes 50/5, 50/4 and 50/43 to provide a water source to Doddridge county PSD. Sun Valley PSD will pick up approx. 65 new customers on the extension and would allow Doddridge county PSD to serve additional residents along Route 23. | M79: Yes | N79: 78 | P79: No | Q79: West Virginia | R79: 2023
A80: Harrison | B80: Short Line PSD | C80: NA | D80: NA | E80: Water System Improvements | F80: General | G80: 4950000 | H80: 3000000 | I80: No Information | J80: No Information | K80: 2681 | L80: This project proposes to replace approximately 50,000 LF of water line ranging in size for 4"" to 8"" in the existing system. These sections of line have been prone to breaks and is causing severe operation and maintenance issues for the District. The District is also proposing to replace sections of valves, hydrants and upgrade their outdated meters to new radio read meters. The District is proposing to replace their existing booster pump station that has severely deteriorated and is at risk of catastrophic failure. | M80: No Information | N80: 79 | P80: No | Q80: West Virginia | R80: 2023
A81: Lincoln | B81: Branchland-Midkiff PSD | C81: NA | D81: NA | E81: 14 Mile Creek Rd. Water Extension Project | F81: General | G81: 2500000 | H81: 2000000 | I81: No Information | J81: No Information | K81: 3278 | L81: Project will extend water service to 26 customers in the 14 Mile Creek Rd. area of Lincoln County. Project includes water lines, booster station and tank. Project would also establish an interconnection with the Logan County PSD. | M81: Yes | N81: 80 | P81: No | Q81: West Virginia | R81: 2023
A82: Lincoln | B82: Branchland-Midkiff PSD | C82: NA | D82: NA | E82: Six Mile Creek Water Extension Project | F82: General | G82: 3000000 | H82: 2000000 | I82: No Information | J82: No Information | K82: 3278 | L82: Project will extend water service to 47 customers in the Six Mile Creek Rd. area of Lincoln County. Project includes water lines, booster station and tank. | M82: Yes | N82: 81 | P82: No | Q82: West Virginia | R82: 2023
A83: Lincoln | B83: Branchland-Midkiff PSD | C83: NA | D83: NA | E83: Two Mile Creek Water Extension Project | F83: General | G83: 3800000 | H83: 2800000 | I83: No Information | J83: No Information | K83: 3278 | L83: Project will extend water service to 61 customers in the Two Mile Creek Rd. and Little Lural Creek areas of Lincoln County. Project includes water lines, booster station and tank. | M83: Yes | N83: 82 | P83: No | Q83: West Virginia | R83: 2023
A84: Lincoln | B84: Branchland-Midkiff PSD | C84: NA | D84: NA | E84: Trace Fork and Hamlin Water Extension Project | F84: General | G84: 3400000 | H84: 2400000 | I84: No Information | J84: No Information | K84: 3278 | L84: Project will extend water service to 61 customers in the Trace Fork and the area between W. Hamlin and 4 Mile Creek. Project includes water lines and a booster station. Project will also eliminate a failing river crossing. | M84: Yes | N84: 83 | P84: No | Q84: West Virginia | R84: 2023
A85: Wayne | B85: Crum PSD | C85: NA | D85: NA | E85: Crum WTP Project | F85: General | G85: 8730000 | H85: 8730000 | I85: No Information | J85: No Information | K85: 3437 | L85: This project will construct an new WTP to serve Crum PSD's 1,345 customers and possibly provide water to the Town of Kermit (524 customers) and the Town of Fort Gay (625 customers). This is a possible consolidation project. | M85: Yes | N85: 84 | P85: No | Q85: West Virginia | R85: 2023
... A135: Berkeley | B135: Berkeley County PSD | C135: NA | D135: NA | E135: Industrial Zone Storage Upgrades | F135: General | G135: 9500000 | H135: 9500000 | I135: No Information | J135: No Information | K135: 34586 | L135: This project will construct an new storage tanks and water mains in the industrial zone area. The District is providing water service to many industrial and commercial companies with little to no redundancy in the storage tanks or water mains. | M135: No | N135: 134 | P135: No | Q135: West Virginia | R135: 2023
A136: Mercer | B136: Mercer County PSD | C136: NA | D136: NA | E136: Pocahontas Water Line Replacement | F136: General | G136: 8119000 | H136: 4059500 | I136: No Information | J136: No Information | K136: No Information | L136: Project includes replacement and upgrade of existing water lines to significantly reduce water loss and allow for the installation of fire hydrants in the area. | M136: No Information | N136: 135 | P136: No | Q136: West Virginia | R136: 2023
A137: McDowell | B137: McDowell County PSD | C137: NA | D137: NA | E137: Elkhorn Ph IV | F137: General | G137: 5610000 | H137: 5610000 | I137: No Information | J137: No Information | K137: No Information | L137: This is the final phase of the Elkhorn Creek water projects. This water project will provide public water service to approx. 375 customers from Keystone to Welch and remove antiquated and unreliable water systems along the route. | M137: Yes | N137: 136 | P137: No | Q137: West Virginia | R137: 2023
A138: McDowell | B138: McDowell County PSD | C138: NA | D138: NA | E138: Jolo Ph V | F138: General | G138: 4253000 | H138: 4253000 | I138: No Information | J138: No Information | K138: No Information | L138: This is the final phase of the Jolo water projects providing water service from the Town of Bradshaw the Virginia state line. This water project will provide public water service to 119 potential customers throughout four areas known as Rockridge, Panther Creek, Barker Ridge and Lex. | M138: Yes | N138: 137 | P138: No | Q138: West Virginia | R138: 2023
A139: McDowell | B139: McDowell County PSD | C139: NA | D139: NA | E139: Anawalt Water System Upgrade | F139: General | G139: 11640000 | H139: 11640000 | I139: No Information | J139: No Information | K139: No Information | L139: This project will replace antiquated and problematic water storage and distribution systems throughout the communities of Anawalt, Leckie, and Jenkinjones. The project will provide public water service to approx. 423 customers. | M139: Yes | N139: 138 | P139: No | Q139: West Virginia | R139: 2023
A140: McDowell | B140: McDowell County PSD | C140: NA | D140: NA | E140: Bridge St. Stream Crossing Project | F140: General | G140: 255000 | H140: 255000 | I140: No Information | J140: No Information | K140: No Information | L140: Proposed project to replace problematic water line stream crossing to provide reliable water and fire protection service to three residential and one commercial customer in the community of Keystone. | M140: Yes | N140: 139 | P140: No | Q140: West Virginia | R140: 2023
A141: Ohio | B141: Triadelphia, Town of | C141: NA | D141: NA | E141: Water System Improvements | F141: General | G141: 4510000 | H141: 4010000 | I141: No Information | J141: No Information | K141: 1215 | L141: This project will include various improvemtns to the WTP and the distribution sysytem. | M141: Yes | N141: 140 | P141: No | Q141: West Virginia | R141: 2023
A142: Wood | B142: Parkersburg Utility Board | C142: NA | D142: NA | E142: WTP PFAS Upgrades | F142: General | G142: No Information | H142: 12000000 | I142: 7403900 | J142: 7403900 | K142: 38189 | L142: ÔøΩThis project will upgrade the water treatment plant to remove PFAS from the source | M142: Yes | N142: 1 | P142: Yes | Q142: West Virginia | R142: 2023
A143: Marshall | B143: Glen Dale, City of | C143: NA | D143: NA | E143: PFAS Filtration Upgrade | F143: General | G143: 2500000 | H143: 2500000 | I143: No Information | J143: No Information | K143: 2495 | L143: Project includes installation of granulated activated carbon filtration with all necessary piping and equipment. | M143: No | N143: 2 | P143: No | Q143: West Virginia | R143: 2023
A144: Harrison | B144: Clarksburg Water Board | C144: NA | D144: NA | E144: Lead Service Line Replacement | F144: Lead | G144: 27025000 | H144: 27025000 | I144: 31033517 | J144: 10276500 | K144: 17686 | L144: Project to replace lead service lines throughout the distribution system. | M144: Yes | N144: 1 | O144: 75 | P144: Yes | Q144: West Virginia | R144: 2023
A145: McDowell | B145: Davy, Town of | C145: NA | D145: NA | E145: Lead Service Line Inventory | F145: Lead | G145: 500000 | H145: 500000 | I145: 1000000 | J145: 500000 | K145: 552 | L145: The project consists of the development of a lead service line inventory and GIS compatible surveying and mapping. | M145: Yes | N145: 2 | O145: 70 | P145: Yes | Q145: West Virginia | R145: 2023
A146: Nicholas | B146: Richwood, City of | C146: NA | D146: NA | E146: Lead Service Line Inventory | F146: Lead | G146: 500000 | H146: 500000 | I146: 1000000 | J146: 500000 | K146: 1095 | L146: The project includes the engineering services necessary to conduct an inventory of lead services and prepare engineering plans for the removal of lead service lines and joints in the City's water distribution system. | M146: Yes | N146: 3 | O146: 70 | P146: Yes | Q146: West Virginia | R146: 2023
A147: Greenbrier | B147: Alderson, Town of | C147: NA | D147: NA | E147: Lead Service Line Replacement | F147: Lead | G147: 615000 | H147: 615000 | I147: 1230000 | J147: 615000 | K147: 2458 | L147: Replace lead service lines throughout the distribution system. | M147: Yes | N147: 4 | O147: 70 | P147: Yes | Q147: West Virginia | R147: 2023
A148: Wyoming | B148: Pineville Municipal Waterworks | C148: NA | D148: NA | E148: Lead Service Line Inventory | F148: Lead | G148: 250000 | H148: 250000 | I148: 500000 | J148: 250000 | K148: 2945 | L148: The project includes the engineering services necessary to conduct an inventory of lead services and prepare engineering plans for the removal of lead service lines in the systems water distribution system, | M148: Yes | N148: 5 | O148: 70 | P148: Yes | Q148: West Virginia | R148: 2023
A149: Greenbrier | B149: Rainelle, Town of | C149: NA | D149: NA | E149: Lead Service Line Inventory | F149: Lead | G149: 500000 | H149: 500000 | I149: 1000000 | J149: 500000 | K149: 1381 | L149: The project consists of the development of a lead service line inventory and GIS compatible surveying and mapping. | M149: Yes | N149: 6 | O149: 55 | P149: Yes | Q149: West Virginia | R149: 2023
A150: McDowell | B150: Gary, City of | C150: NA | D150: NA | E150: Lead Service Line Inventory | F150: Lead | G150: 500000 | H150: 500000 | I150: 1000000 | J150: 500000 | K150: 1633 | L150: This project includes the engineering services necessary to conduct an inventory of lead services and prepare engineering plans for the removal of lead service lines in the City's distribution system. | M150: Yes | N150: 7 | O150: 55 | P150: Yes | Q150: West Virginia | R150: 2023
A151: Hancock | B151: Oakland PSD | C151: NA | D151: NA | E151: Lead Service Line Replacement | F151: Lead | G151: No Information | H151: No Information | I151: 500000 | J151: 250000 | K151: 1846 | L151: This project includes development of a lead service line inventory and replacing lead service lines throughout the distribution system. | M151: Yes | N151: 8 | O151: 55 | P151: Yes | Q151: West Virginia | R151: 2023
A152: McDowell | B152: Welch, City of | C152: NA | D152: NA | E152: Lead Service Line Inventory | F152: Lead | G152: 500000 | H152: 500000 | I152: 1000000 | J152: 500000 | K152: 2907 | L152: The project includes the engineering services necessary to conduct an inventory of lead services and prepare engineering plans for the removal of lead service lines and joints in the City's water distribution system. | M152: Yes | N152: 9 | O152: 55 | P152: Yes | Q152: West Virginia | R152: 2023
A153: Upshur | B153: Mount Hope Water Assoc. | C153: NA | D153: NA | E153: Lead Service Line Inventory | F153: Lead | G153: 200000 | H153: 200000 | I153: 200000 | J153: No Information | K153: 2870 | L153: Project to determine the service line material used from the meter to the customers structure. | M153: No | N153: 10 | O153: 50 | P153: Yes | Q153: West Virginia | R153: 2023
A154: Mercer | B154: Athens, Town of | C154: NA | D154: NA | E154: Lead Service Line Inventory | F154: Lead | G154: 25000 | H154: 25000 | I154: No Information | J154: No Information | K154: 4802 | L154: Project to perform an inventory of lead service line in the system. Included in this inventory will also be a proposed plan for replacement of the lines and modified sampling locations according to what is discovered. | M154: No Information | N154: 11 | O154: 50 | P154: No | Q154: West Virginia | R154: 2023
A155: Monroe | B155: Red Sulphur PSD | C155: NA | D155: NA | E155: Service Line Replacement Project | F155: Lead | G155: 2277600 | H155: 2277600 | I155: No Information | J155: No Information | K155: 5352 | L155: The project consists of the development of a lead service line inventory and GIS compatible surveying and mapping and the anticipated replacement of approx. 5,000 lf of lead service line replacement from the main to the home. | M155: No Information | N155: 12 | O155: 50 | P155: No | Q155: West Virginia | R155: 2023
A156: Nicholas | B156: Summersville, City of | C156: NA | D156: NA | E156: Lead Service Line Inventory | F156: Lead | G156: 500000 | H156: 500000 | I156: No Information | J156: No Information | K156: 5574 | L156: This project includes the engineering services necessary to conduct an inventory of lead services and prepare engineering plans for the removal of lead service lines in the City's distribution system. | M156: No | N156: 13 | O156: 50 | P156: No | Q156: West Virginia | R156: 2023
...
